<?xml version="1.0" encoding="utf-8"?>
<etl>
    <field>
        <key>brand</key>
        <actions>
            <action>remove-escapechar</action>
            <action>case-insensitive</action>
            <action>split-en</action>
        </actions>
        <values>
            <value>\u7231\u601d\u97e9</value>
            <value>OEHE</value>
            <value>212CCXII</value>
            <value>A.J.BB</value>
            <value>a02</value>
            <value>A21</value>
            <value>aape</value>
            <value>ADAM LIPPES</value>
            <value>Adidas/\u963f\u8fea\u8fbe\u65af</value>
            <value>AGNONA</value>
            <value>Akseries</value>
            <value>ALBERTA FERRETTI</value>
            <value>ALESSANDRA RICH</value>
            <value>ALEXANDER MCQUEEN</value>
            <value>ALEXANDER WANG</value>
            <value>ALICE + OLIVIA</value>
            <value>ALICE CICOLINI</value>
            <value>ALISON LOU</value>
            <value>ALTUZARRA</value>
            <value>ALVARO</value>
            <value>AMII</value>
            <value>ANNA SUI</value>
            <value>ANTA/\u5b89\u8e0f</value>
            <value>Apple</value>
            <value>AR</value>
            <value>Asics/\u4e9a\u745f\u65af</value>
            <value>ASOBIO</value>
            <value>AZVF</value>
            <value>BALENCIAGA</value>
            <value>BALMAIN</value>
            <value>Bape(\u8863\u670d\u6f6e\u724c)</value>
            <value>BEBEERU</value>
            <value>BELLE</value>
            <value>BLUESHEROES</value>
            <value>BOTTEGA VENETA</value>
            <value>broadcast/\u64ad</value>
            <value>BURBERRY</value>
            <value>C&amp;2K</value>
            <value>C&amp;A</value>
            <value>C2\u6f6e\u671d</value>
            <value>Cache-Cache</value>
            <value>cadidl</value>
            <value>CALVIN KLEIN UNDERWEAR</value>
            <value>celine</value>
            <value>Chanel</value>
            <value>CHEVIGNON</value>
            <value>CHLOE</value>
            <value>CHRISTIAN LOUBOUTIN</value>
            <value>Coach</value>
            <value>Columbia/\u54e5\u4f26\u6bd4\u4e9a</value>
            <value>COMME DES GARCONS</value>
            <value>CONNER LEE</value>
            <value>Converse/\u5321\u5a01</value>
            <value>CRW&amp;ESTR</value>
            <value>DAZZLE</value>
            <value>de fonseca</value>
            <value>deerejack</value>
            <value>Defonseca</value>
            <value>DeskMate</value>
            <value>devil nut</value>
            <value>DHUB</value>
            <value>Dickies</value>
            <value>Dior</value>
            <value>Dirs</value>
            <value>DKNY</value>
            <value>DoaVsng</value>
            <value>DOLCE &amp; GABBANA</value>
            <value>Dunhilll</value>
            <value>DUSSI</value>
            <value>E-LAND</value>
            <value>EMILIO PUCCI</value>
            <value>erke/\u9e3f\u661f\u5c14\u514b</value>
            <value>ESPRIT</value>
            <value>ESVT</value>
            <value>evisu</value>
            <value>FENDI</value>
            <value>Five Plus</value>
            <value>flowerscoming</value>
            <value>FOREVER21</value>
            <value>G2000</value>
            <value>Gen/\u7b80</value>
            <value>George Walk</value>
            <value>Giorgio Armani</value>
            <value>GIVENCHY</value>
            <value>GOODENOUGH</value>
            <value>GRACEMMXIII</value>
            <value>G-STAR</value>
            <value>GUCCI</value>
            <value>Guess</value>
            <value>Gurun vani</value>
            <value>GXG</value>
            <value>gxg.jeans</value>
            <value>H&amp;M</value>
            <value>HALSTON HERITAGE</value>
            <value>heipao</value>
            <value>Hermes</value>
            <value>Honeys</value>
            <value>Howoreasy</value>
            <value>HRTIS</value>
            <value>Hugo Boss</value>
            <value>IJOY</value>
            <value>izzue</value>
            <value>JACK JOHNNY</value>
            <value>jack wolfshin/\u72fc\u722a</value>
            <value>JackJones</value>
            <value>Jasonwood</value>
            <value>JIMMY CHOO</value>
            <value>JUSTYLE</value>
            <value>K328ICACNE</value>
            <value>kailas/\u51ef\u4e50\u77f3</value>
            <value>Kappa/\u80cc\u9760\u80cc</value>
            <value>Kate spade new York</value>
            <value>Kenzo</value>
            <value>KNNE</value>
            <value>LACOSTE</value>
            <value>lagogo</value>
            <value>LANVIN</value>
            <value>Last Order</value>
            <value>Lee</value>
            <value>Levi\u2019s</value>
            <value>Lining/\u674e\u5b81</value>
            <value>LOEWE</value>
            <value>LOJO</value>
            <value>Louis Vuitton</value>
            <value>LUCKY OZASEC</value>
            <value>M2monline</value>
            <value>MANGO</value>
            <value>Marc jacbos</value>
            <value>Marisfrolg</value>
            <value>MCM</value>
            <value>Me&amp;City</value>
            <value>merdor</value>
            <value>mineeor</value>
            <value>mishka</value>
            <value>Miu Miu</value>
            <value>Mo&amp;Co</value>
            <value>moonicer</value>
            <value>Moschino</value>
            <value>Mr.benyou</value>
            <value>MUJI(\u65e0\u5370\u826f\u54c1)</value>
            <value>MULBERRY</value>
            <value>N+a\u7eb3\u8fea\u4e9a</value>
            <value>NAMP</value>
            <value>NEW BALANCE/\u65b0\u767e\u4f26</value>
            <value>NEWS</value>
            <value>Nike/\u8010\u514b</value>
            <value>NUMBER(N)INE</value>
            <value>OCSIN</value>
            <value>OLMOS</value>
            <value>ONEBUYE</value>
            <value>ONLY</value>
            <value>OVBE</value>
            <value>PASS</value>
            <value>PatriziaPepe</value>
            <value>Paul Frank</value>
            <value>Paul smith</value>
            <value>Peak/\u5339\u514b</value>
            <value>PLAYBOY PHYSICAL</value>
            <value>PLOVER</value>
            <value>Prada</value>
            <value>Puma/\u5f6a\u9a6c</value>
            <value>QUIKSILVER</value>
            <value>Rebecca minkoff</value>
            <value>REFUO</value>
            <value>ROWILUX</value>
            <value>RYRY</value>
            <value>S.DEER</value>
            <value>Salvatore Ferragamo</value>
            <value>Selected</value>
            <value>SENKU</value>
            <value>SIMWOOD</value>
            <value>Skechers/\u65af\u51ef\u5947</value>
            <value>Soinku\u6f6e\u578b\u5e93</value>
            <value>STAY REAL</value>
            <value>STELLA MCCARTNEY</value>
            <value>stussy</value>
            <value>supreme</value>
            <value>TBA</value>
            <value>the north face/\u5317\u8138</value>
            <value>Timberland/\u6dfb\u67cf\u5c9a</value>
            <value>TOD'S</value>
            <value>TOM FORD</value>
            <value>TOMMYHILFIGER</value>
            <value>TOPOT</value>
            <value>Toread/\u63a2\u8def\u8005</value>
            <value>TRENDIANO</value>
            <value>UGG</value>
            <value>Uniqlo</value>
            <value>UO</value>
            <value>UR</value>
            <value>UYUK</value>
            <value>VALENTINO</value>
            <value>VANS</value>
            <value>VEROMODA</value>
            <value>VERSACE</value>
            <value>Victoria gossip</value>
            <value>viishow</value>
            <value>Visvim(\u978b\u65e5\u672c\u6f6e\u724c)</value>
            <value>Vivienne westwood</value>
            <value>VIVIENNE WESTWOOD ANGLOMANIA</value>
            <value>X-Large</value>
            <value>XTEP/\u7279\u6b65</value>
            <value>y-3</value>
            <value>Yellow Earth</value>
            <value>YE'SBYYESIR</value>
            <value>YUTUBOY</value>
            <value>ZARA</value>
            <value>ZERO</value>
            <value>ZK</value>
            <value>ZORMO</value>
            <value>ZPPSN</value>
            <value>ZZ&amp;FF</value>
            <value>\u963f\u65af\u987f\u540d\u7235</value>
            <value>\u963f\u4f9d\u83b2</value>
            <value>\u54ce\u5e03\u54ce\u5076</value>
            <value>\u827e\u84d3\u6021</value>
            <value>\u827e\u8303\u8fbe</value>
            <value>\u827e\u683cEtam</value>
            <value>\u827e\u683cWEEKEND</value>
            <value>\u827e\u83b1\u4f9d</value>
            <value>\u827e\u76fc\u5e0c</value>
            <value>\u7231\u9edb\u59ec</value>
            <value>\u7231\u5824\u513f</value>
            <value>\u7231\u5c1a\u6f6e\u6d41</value>
            <value>\u7231\u5c1a\u8857\u811a</value>
            <value>\u7231\u6b23\u8d1d\u8d1d</value>
            <value>\u5965\u5e1d\u4f26(aodilun)</value>
            <value>\u5965\u5eb7</value>
            <value>\u5965\u5eb7(Aokang)</value>
            <value>\u5965\u5170\u72ee</value>
            <value>\u5965\u65af\u9999</value>
            <value>\u6fb3\u5947\u7f8e</value>
            <value>\u5df4\u91cc\u7279\u838e</value>
            <value>\u5df4\u9c81\u7279(Brloote)</value>
            <value>\u82ad\u59ae\u8bd7</value>
            <value>\u767d\u9886\u4e3d\u4eba</value>
            <value>\u767e\u7231\u5973\u795e</value>
            <value>\u767e\u5b9d\u76fe</value>
            <value>\u767e\u5bb6\u597d</value>
            <value>\u767e\u6d1b\u5b89</value>
            <value>\u767e\u5e74\u7eaa\u5ff5(centenary)</value>
            <value>\u767e\u56fe</value>
            <value>\u767e\u5b9c\u5a07</value>
            <value>\u4f70\u601d\u68b5\u59ae</value>
            <value>\u67cf\u8fea\u9a6c\u4e01(BaiDiMartin)</value>
            <value>\u67cf\u4e1d\u8335</value>
            <value>\u73ed\u7c73\u6d1b</value>
            <value>\u73ed\u5c3c\u8def(Baleno)</value>
            <value>\u90a6\u695a\u4ed5</value>
            <value>\u4fdd\u7f57\u76d6\u5e1d</value>
            <value>\u5821\u72ee\u9f99(bossini)</value>
            <value>\u7206\u773c(BQODQO)</value>
            <value>\u5317\u6781\u7ed2(Bejirog)</value>
            <value>\u8d1d\u68b5\u8bd7</value>
            <value>\u84d3\u5c14</value>
            <value>\u7b28\u5148\u751f</value>
            <value>\u6bd4\u83f2\u529b(BEVERRY)</value>
            <value>\u78a7\u53f6\u4e91\u53f0</value>
            <value>\u6ce2\u53f8\u767b</value>
            <value>\u6ce2\u65af\u8482\u742a</value>
            <value>\u5e1b\u8587\u513f</value>
            <value>\u640f\u62d3</value>
            <value>\u5e03\u5e03\u53d1\u73b0</value>
            <value>\u5e03\u83b1\u5e0c\u5c14\u987f</value>
            <value>\u6b65\u514b\u97e6\u65af\u62d3</value>
            <value>\u624d\u5b50</value>
            <value>\u624d\u5b50(TRIES)</value>
            <value>\u6f6e\u8def\u601d</value>
            <value>\u6f6e\u65e0\u754c</value>
            <value>\u627f\u53d1</value>
            <value>\u57ce\u5e02\u524d\u7aef(chengshiqianduan)</value>
            <value>\u9a70\u7434</value>
            <value>\u521d\u68c9</value>
            <value>\u521d\u8bed</value>
            <value>\u7eaf\u675f</value>
            <value>\u6df3\u6b63</value>
            <value>\u8fbe\u8299\u59ae</value>
            <value>\u5927\u536b\u7c73\u52d2(David miller)</value>
            <value>\u5927\u536b\u5c71(dave hill)</value>
            <value>\u6234\u7ef4\u674e</value>
            <value>\u4e39\u5c14\u66fc\u5e1d</value>
            <value>\u4e39\u5c14\u65af\u7279</value>
            <value>\u4e39\u6770\u4ed5(DAN JIE SHI)</value>
            <value>\u4e39\u96f7\u65af</value>
            <value>\u4e39\u742a\u6770\u601d</value>
            <value>\u4e39\u601d\u9732</value>
            <value>\u4e39\u59ff\u5974</value>
            <value>\u7a3b\u8349\u4eba(MEXICAN)</value>
            <value>\u5fb7\u5c14\u52a0\u591a(Delocrd)</value>
            <value>\u72c4\u6d3e\u65af</value>
            <value>\u8fea\u82ac.\u7490\u5609</value>
            <value>\u8fea\u83b1\u56fe</value>
            <value>\u8fea\u8056\u51ef\u5c3c</value>
            <value>\u8fea\u58eb\u5c3cDisney</value>
            <value>\u5730\u7403\u57ce(DIQIUCHENG)</value>
            <value>\u5730\u7d20</value>
            <value>\u5e1d\u51e1\u5188</value>
            <value>\u5e1d\u5ba2(Dickies)</value>
            <value>\u5e1d\u5c3c\u683c\u745e</value>
            <value>\u789f\u5c39\u604b</value>
            <value>\u4e1c\u5e1d\u540d\u574a</value>
            <value>\u4e1c\u5947\u53e4\u9053(DonqeGoodal)</value>
            <value>\u5cbd\u5802\u79be</value>
            <value>\u90fd\u8a00</value>
            <value>\u675c\u5c3c\u5965(DUNIAO)</value>
            <value>\u76fe\u72d0</value>
            <value>\u9102\u5c14\u591a\u65af</value>
            <value>\u9cc4\u9c7c\u6064</value>
            <value>\u6069\u5c1a</value>
            <value>\u6069\u88f3</value>
            <value>\u6cd5\u8482\u5a1c</value>
            <value>\u6cd5\u51ef\u66fc(FAKAIMAN)</value>
            <value>\u6cd5\u739b\u838e(FAVMARTHA)</value>
            <value>\u6cd5\u7426\u746a\u5e1d</value>
            <value>\u6cd5\u8428\u5974</value>
            <value>\u6cd5\u5c0a\u5c3c</value>
            <value>\u51e1\u5ba2\u8bda\u54c1</value>
            <value>\u51e1\u8f6c(FANZHUAN)</value>
            <value>\u68b5\u5965\u59ff</value>
            <value>\u68b5\u8482\u831c\u5a05</value>
            <value>\u82b3\u598d\u4e3d\u82b8</value>
            <value>\u975e\u51e1\u9886\u8896</value>
            <value>\u7c89\u7ea2\u5927\u5e03\u5a03\u5a03</value>
            <value>\u98ce\u5c1a\u7f0c\u8574</value>
            <value>\u67ab\u83b2\u679c</value>
            <value>\u67ab\u8863\u7ef5\u9970</value>
            <value>\u67ab\u4e4b\u73b2</value>
            <value>\u5f17\u8a79\u660c</value>
            <value>\u798f\u5c14\u4eae</value>
            <value>\u5bcc\u8d35\u9e1f</value>
            <value>\u76d6\u749e(GAP)</value>
            <value>\u7518\u4e43\u8fea</value>
            <value>\u6e2f\u68c9</value>
            <value>\u9ad8\u68b5</value>
            <value>\u54e5\u5f1f</value>
            <value>\u6b4c\u8389\u5a05</value>
            <value>\u6b4c\u7c73\u83b2</value>
            <value>\u6b4c\u8428\u5a05</value>
            <value>\u6b4c\u8d44\u5983</value>
            <value>\u9769\u58eb\u58eb</value>
            <value>\u683c\u82ad\u5a1c</value>
            <value>\u683c\u84dd\u51ef</value>
            <value>\u683c\u59ae\u5a05</value>
            <value>\u683c\u7f07\u5983</value>
            <value>\u516c\u725b\u4e16\u5bb6(G.N.Shi Jia)</value>
            <value>\u5bab\u5974</value>
            <value>\u52fe\u80a1</value>
            <value>\u53e4\u83b1\u767b(GODLIKE)</value>
            <value>\u53e4\u5947\u5929\u4f26</value>
            <value>\u53e4\u4ed5\u5361\u7279(GUSSKATER)</value>
            <value>\u53e4\u4f9d\u820d</value>
            <value>\u54c8\u68ee</value>
            <value>\u6d77\u6f9c\u4e4b\u5bb6(HEILAN HOME)</value>
            <value>\u61a8\u539a\u7687\u540e</value>
            <value>\u97e9\u8d1d\u4f0a\u90fd</value>
            <value>\u97e9\u535f</value>
            <value>\u97e9\u90fd\u8863\u820d</value>
            <value>\u97e9\u5c3c\u59ff</value>
            <value>\u97e9\u5915\u6b27</value>
            <value>\u97e9\u96c5\u8431</value>
            <value>\u97e9\u4f9d\u6b23</value>
            <value>\u608d\u98ce</value>
            <value>\u608d\u9e7f</value>
            <value>\u7ff0\u5ea6(HANDU)</value>
            <value>\u597d\u4e1c\u5bb6</value>
            <value>\u597d\u8863\u7537\u5bfb</value>
            <value>\u7693\u5ddd\u5d0e</value>
            <value>\u7693\u987f(HAUTTON)</value>
            <value>\u9ed1\u5148\u751f</value>
            <value>\u4ea8\u5b87</value>
            <value>\u6052\u6f6e(HengChao)</value>
            <value>\u6052\u6e90\u7965(HYX)</value>
            <value>\u7ea2\u90fd</value>
            <value>\u7ea2\u8c46(Hodo)</value>
            <value>\u7ea2\u873b\u8713</value>
            <value>\u7ea2\u873b\u8713(RED DRAGONFLY)</value>
            <value>\u7ea2\u4eba</value>
            <value>\u7ea2\u8896</value>
            <value>\u5b8f\u6d69</value>
            <value>\u9e3f\u6cf0\u6625\u5929</value>
            <value>\u82b1\u74e3\u96e8\u4e16\u5bb6</value>
            <value>\u82b1\u5983\u4e16\u5bb6</value>
            <value>\u82b1\u82b1\u516c\u5b50(PLAYBOY)</value>
            <value>\u82b1\u7530\u96c5\u7ec7</value>
            <value>\u534e\u83f2.\u578b\u683c(FAIRWHALE SHAKE)</value>
            <value>\u73af\u7403</value>
            <value>\u5fbd\u82cf\u513f</value>
            <value>\u56de\u529b(Warrior)</value>
            <value>\u706b\u8f6e</value>
            <value>\u5409\u79be\u4f0a\u5609</value>
            <value>\u5409\u666e(JEEP)</value>
            <value>\u5409\u666e\u76fe(NIAN JEEP)</value>
            <value>\u5409\u666e\u6218\u8f66(JIPUZHANCHE)</value>
            <value>\u6781\u5730\u9e25</value>
            <value>\u9701\u84dd</value>
            <value>\u4f73\u8863\u540d\u54c1</value>
            <value>\u7b80\u8349</value>
            <value>\u7b80\u88d4\u9177(JIANYIKU)</value>
            <value>\u6c5f\u5357\u5e03\u8863</value>
            <value>\u5a07\u8299\u838e</value>
            <value>\u5a07\u4eba\u871c\u96ea</value>
            <value>\u5a07\u8212\u9edb</value>
            <value>\u9a84\u59e3\u592b\u4eba</value>
            <value>\u6770\u5965\u601d\u7433</value>
            <value>\u6770\u8c6a</value>
            <value>\u6770\u514b\u743c\u65af(Jack Jones)</value>
            <value>\u6770\u68ee\u8fea\u4e9a</value>
            <value>\u6770\u897f\u4f0d</value>
            <value>\u6377\u514b\u83b1\u65af</value>
            <value>\u91d1\u7334</value>
            <value>\u91d1\u91cc\u660a\u7279</value>
            <value>\u91d1\u5229\u6765(Goldlion)</value>
            <value>\u91d1\u6ceb\u96c5</value>
            <value>\u9526\u6f9c\u4f0a\u60a6</value>
            <value>\u52b2\u9738\u7537\u88c5(K-Boxing)</value>
            <value>\u4e5d\u7267\u738b(JOEONE)</value>
            <value>\u7396\u7199</value>
            <value>\u4e3e\u7ffc\u738b\u5b50</value>
            <value>\u5361\u5bbe(CABBEEN)</value>
            <value>\u5361\u4e39\u8def</value>
            <value>\u5361\u5e1d\u4e50\u9cc4\u9c7c(CARTELO)</value>
            <value>\u5361\u83f2\u5c3c</value>
            <value>\u5361\u6d1b\u5c14\u83f2</value>
            <value>\u5361\u6d1b\u4ed9</value>
            <value>\u5361\u739b(KAMA)</value>
            <value>\u5361\u739b\u5a05</value>
            <value>\u5361\u5723\u4ed5</value>
            <value>\u5361\u7d20\u4f9d</value>
            <value>\u51ef\u767b\u535a</value>
            <value>\u51ef\u738b\u5e1d</value>
            <value>\u5eb7\u5948</value>
            <value>\u73c2\u5361\u8299</value>
            <value>\u79d1\u7ef4\u4f9d</value>
            <value>\u53ef\u7c73\u679c\u679c</value>
            <value>\u53ef\u60c5\u5c0f\u7f8e</value>
            <value>\u514b\u91cc\u897f\u8499(CKLIXIMEN)</value>
            <value>\u514b\u6797\u79d1\u65af</value>
            <value>\u5feb\u4e50\u5609\u4eba</value>
            <value>\u5feb\u4e50\u739b\u4e3d</value>
            <value>\u5feb\u9e7f</value>
            <value>\u9b41\u4f9d</value>
            <value>\u9614\u8272</value>
            <value>\u83b1\u5361\u91d1\u987f</value>
            <value>\u83b1\u6d3e\u8482</value>
            <value>\u5170\u60c5\u82b3</value>
            <value>\u84dd\u5e15\u4f69\u5c3c</value>
            <value>\u84dd\u838e\u57df</value>
            <value>\u84dd\u5c71\u6c50</value>
            <value>\u84dd\u4e07</value>
            <value>\u84dd\u96e8\u8776\u4f9d</value>
            <value>\u84dd\u6708\u828a\u9b45</value>
            <value>\u862d\u83c1</value>
            <value>\u6717\u8863\u8d1d(langyibei)</value>
            <value>\u6d6a\u838e(LangSha)</value>
            <value>\u4e50\u753a</value>
            <value>\u96f7\u8fea\u535a\u5fb7</value>
            <value>\u9ece\u7eaf(LICHUN)</value>
            <value>\u674e\u7ef4\u65af(Levi's)</value>
            <value>\u4e3d\u5fb7\u7f26</value>
            <value>\u5229\u90ce</value>
            <value>\u5229\u90ce(LILANZ)</value>
            <value>\u5229\u7ec5\u72d0(lishenhu)</value>
            <value>\u83b2\u9999\u9e1f</value>
            <value>\u826f\u54c1\u5154\u5b50</value>
            <value>\u9753\u838e\u7eee</value>
            <value>\u88c2\u5e1b</value>
            <value>\u90bb\u5bb6\u5929\u4f7f</value>
            <value>\u7433\u827e\u7433</value>
            <value>\u7433\u6735\u513f</value>
            <value>\u4f36\u7f8a</value>
            <value>\u96f6\u67d2\u96f6\u634c</value>
            <value>\u6d41\u6c13\u5154</value>
            <value>\u80e7\u7530\u96c5\u7ec7</value>
            <value>\u80e7\u6708\u4e3d\u598d</value>
            <value>\u8def\u5fb7\u6069</value>
            <value>\u8def\u8def\u4f73</value>
            <value>\u9732\u4e1d\u51ef\u65af</value>
            <value>\u4f26\u6566\u96fe(London Fog)</value>
            <value>\u7f57\u8499</value>
            <value>\u9a86\u9a7c(CAMEL)</value>
            <value>\u9a86\u9a7c\u52a8\u611f(camel active)</value>
            <value>\u73de\u4fd0\u5a05</value>
            <value>\u843d\u96c1\u838e</value>
            <value>\u5415\u5361\u7fc1</value>
            <value>\u9a6c\u514b\u534e\u83f2(FAIRWHALE)</value>
            <value>\u739b\u80af(MaueKen)</value>
            <value>\u739b\u4ebf\u5c1a(MAYISHANG)</value>
            <value>\u8682\u8681\u4e4b\u604b</value>
            <value>\u9ea6\u7235\u65af\u8482</value>
            <value>\u9ea6\u5361\u5e0c\u59ae</value>
            <value>\u9ea6\u5d0e\u8bfa</value>
            <value>\u9ea6\u7eee\u7ee3</value>
            <value>\u6f2b\u82ad\u68ee</value>
            <value>\u7f8e\u8776\u9edb</value>
            <value>\u7f8e\u4e3d\u5ae6</value>
            <value>\u7f8e\u83b2\u9999</value>
            <value>\u7f8e\u59ae\u59ec</value>
            <value>\u7f8e\u7279\u65af\u90a6\u5a01(metersbonwe)</value>
            <value>\u7f8e\u5929\u4f9d\u5942</value>
            <value>\u7f8e\u8335\u513f</value>
            <value>\u7f8e\u8db3\u9686</value>
            <value>\u9b45\u529b\u82ad\u85dc</value>
            <value>\u8499\u52a0</value>
            <value>\u8499\u6c83\u513f</value>
            <value>\u6aac\u4f0a</value>
            <value>\u68a6\u5e7b\u4fcf\u4f73\u4eba</value>
            <value>\u68a6\u6d01\u8389</value>
            <value>\u68a6\u8212\u96c5</value>
            <value>\u68a6\u7279\u5a07</value>
            <value>\u68a6\u6615</value>
            <value>\u8c1c\u5c1a\u59ae</value>
            <value>\u7c73\u6d1b\u514b</value>
            <value>\u7c73\u65af\u5eb7</value>
            <value>\u68c9\u8bb0</value>
            <value>\u6dfc\u5999</value>
            <value>\u540d\u95e8\u671b\u8db3</value>
            <value>\u94ed\u7235\u98ce</value>
            <value>\u7f2a\u7f2a</value>
            <value>\u6469\u4e9a\u8bfa</value>
            <value>\u9b54\u706f\u8bda\u5821</value>
            <value>\u8309\u6c40</value>
            <value>\u83ab\u5361\u59ae\u96ea</value>
            <value>\u83ab\u857e\u853b\u857e</value>
            <value>\u58a8\u8bfa\u4f70MANOBLE</value>
            <value>\u6728\u4f4e\u8bed</value>
            <value>\u6728\u4f4e\u8bed(MUDIYU)</value>
            <value>\u6728\u679c\u679c\u6728</value>
            <value>\u6728\u6797\u68ee</value>
            <value>\u6728\u6797\u68ee(MULINSEN)</value>
            <value>\u6728\u725b\u725b\u9a6c</value>
            <value>\u6728\u771f\u4e86</value>
            <value>\u6155\u5361\u970f</value>
            <value>\u6155\u6d3e\u8fea</value>
            <value>\u6155\u5854\u5983</value>
            <value>\u7eb3\u8fea\u4e9a(N+a)</value>
            <value>\u5357\u6781\u4eba(Nanjiren)</value>
            <value>\u59ae\u535f</value>
            <value>\u725b\u5934\u914b\u957f</value>
            <value>\u8bfa\u5a32</value>
            <value>\u5973\u4eba\u955c</value>
            <value>\u5662\u90b8\u535a</value>
            <value>\u6b27\u6d1b\u5361\u8fea</value>
            <value>\u6b27\u838e</value>
            <value>\u6b27\u8bd7\u7f57\u5170</value>
            <value>\u6b27\u65f6\u529b</value>
            <value>\u6b27\u4ee5\u7eaf\u7537</value>
            <value>\u5e15\u5b9d\u7f07</value>
            <value>\u5e15\u8fbe\u7d22</value>
            <value>\u4f69\u5170\u7279</value>
            <value>\u54c1\u7acb(PINLI)</value>
            <value>\u84b2\u4f18\u8513</value>
            <value>\u4e03\u683c\u683c</value>
            <value>\u4e03\u5339\u72fc(SEPTWOLVES)</value>
            <value>\u67d2\u724c(SEVEN)</value>
            <value>\u7eee\u5f64\u5c0f\u9547</value>
            <value>\u5343\u767e\u5ea6</value>
            <value>\u5343\u83b9</value>
            <value>\u5343\u7eb8\u9e64(QZHIHE)</value>
            <value>\u6d45\u672b</value>
            <value>\u5f3a\u4eba</value>
            <value>\u4e54\u4e39</value>
            <value>\u4e54\u4e39\u683c\u5170(Joedon Golan)</value>
            <value>\u4fcf\u60c5\u6735</value>
            <value>\u4fcf\u60c5\u82ac</value>
            <value>\u4fcf\u60a6\u59ae</value>
            <value>\u9752\u6625\u4f34\u4fa3</value>
            <value>\u9752\u679c</value>
            <value>\u60c5\u83b2\u513f</value>
            <value>\u743c\u745b</value>
            <value>\u79cb\u6c34\u4f0a\u4eba</value>
            <value>\u79cb\u6c34\u518d\u5ea6</value>
            <value>\u79cb\u4e4b\u5317\u7eac</value>
            <value>\u5168\u5c1a\u7f8e</value>
            <value>\u70ed\u98ce</value>
            <value>\u4eba\u672c</value>
            <value>\u82ae\u83e1</value>
            <value>\u82ae\u5a55</value>
            <value>\u95f0\u6977</value>
            <value>\u8d5b\u65af\u7279</value>
            <value>\u8d5b\u9014</value>
            <value>\u4e09.\u56f4.\u4f20.\u8bf4</value>
            <value>\u4e09\u5f69</value>
            <value>\u4e09\u798f(SANFU)</value>
            <value>\u68ee\u96f7\u53f8(SENLEIS)</value>
            <value>\u68ee\u6797\u6c34\u4ed9</value>
            <value>\u68ee\u9a6c(Semir)</value>
            <value>\u68ee\u5bbf</value>
            <value>\u6c99\u9a70</value>
            <value>\u838e\u8d1d\u831c</value>
            <value>\u838e\u5409\u5c3c</value>
            <value>\u838e\u7c73\u4e50</value>
            <value>\u6749\u6749(FIRS)</value>
            <value>\u886b\u6b65</value>
            <value>\u95ea\u6b65</value>
            <value>\u5c1a\u53e4\u4e3b\u4e49</value>
            <value>\u5c1a\u8389\u742a</value>
            <value>\u5c1a\u829d\u604b</value>
            <value>\u88f3\u66fc</value>
            <value>\u88f3\u4f0a\u5c45</value>
            <value>\u5c11\u7237\u5f88\u5fd9</value>
            <value>\u795e\u5dde\u9a86\u9a7c(earth camel)</value>
            <value>\u6c88\u8863\u5bb8</value>
            <value>\u5347\u5b87\u7490\u6cd5\u96c5</value>
            <value>\u5723\u5f97\u897f</value>
            <value>\u5723\u9ad8</value>
            <value>\u5723\u6717\u535a\u58eb(SHENGLANGBOSS)</value>
            <value>\u8bd7\u7bc7</value>
            <value>\u5341\u7c73\u5e03</value>
            <value>\u62fe\u8d27</value>
            <value>\u517d\u9738</value>
            <value>\u517d\u738b</value>
            <value>\u59dd\u6f2b</value>
            <value>\u6dd1\u5973\u5c4b</value>
            <value>\u8212\u4e00\u65af</value>
            <value>\u53f8\u5947\u9686(Siqilong)</value>
            <value>\u601d\u83b1\u5fb7(selected)</value>
            <value>\u65af\u8482\u82ac\u59ae</value>
            <value>\u65af\u7c73\u5c14</value>
            <value>\u901f\u5199</value>
            <value>\u5854\u91cc\u5c3c\u6b27(La\u2019terraneo)</value>
            <value>\u53f0\u6e7e\u9a86\u9a7c</value>
            <value>\u81fa\u4e1d</value>
            <value>\u592a\u5e73\u9e1f</value>
            <value>\u592a\u5b50\u83b2</value>
            <value>\u592a\u5b50\u9f99(TEDELON)</value>
            <value>\u6cf0\u548c\u6e90</value>
            <value>\u6c64\u59c6\u65af</value>
            <value>\u5510\u72ee(TonLion)</value>
            <value>\u5a9e\u82ae</value>
            <value>\u7f07\u53ef</value>
            <value>\u62d3\u8def\u8005(pioneercamp)</value>
            <value>\u62d3\u4e00(TUOYI)</value>
            <value>\u5916\u83b1\u4f9d</value>
            <value>\u738b\u83f2\u513f</value>
            <value>\u5a01\u53ef\u591a(VICUTU)</value>
            <value>\u5a01\u52b3\u4e39\u601d</value>
            <value>\u5a01\u4e16\u7c73\u90a6</value>
            <value>\u7ef4\u6770\u65af(WINJEANS)</value>
            <value>\u7ef4\u7edc\u65af</value>
            <value>\u9b4f\u664b\u98ce\u5ea6</value>
            <value>\u6e29\u59ae\u59ff</value>
            <value>\u821e\u7fbd\u4f26\u6bd4</value>
            <value>\u897f\u4f2f\u5229\u5a1c</value>
            <value>\u897f\u6751\u540d\u7269</value>
            <value>\u897f\u745e</value>
            <value>\u897f\u838e\u5c14</value>
            <value>\u897f\u57df\u9a86\u9a7c</value>
            <value>\u897f\u5b50\u95a3</value>
            <value>\u5e0c\u4f2f\u540d</value>
            <value>\u5e0c\u9edb\u6708</value>
            <value>\u7199\u4e16\u754csllsky</value>
            <value>\u559c\u65af\u7279</value>
            <value>\u590f\u5c14\u7ef4\u7eb3</value>
            <value>\u590f\u51fd</value>
            <value>\u7ea4\u6155(XIANMU)</value>
            <value>\u7ea4\u79cb\u68a6</value>
            <value>\u9999\u7231\u871c</value>
            <value>\u9999\u8299\u66fc</value>
            <value>\u9999\u60c5\u59ff</value>
            <value>\u60f3\u5ddd</value>
            <value>\u5411\u4f50</value>
            <value>\u978b\u5c0f\u4e8c</value>
            <value>\u65b0\u767e\u4f26\u9886\u8dd1</value>
            <value>\u99a8\u8bd7\u96c5\u60a6</value>
            <value>\u5e78\u798f\u65f6\u5149(happytime)</value>
            <value>\u79c0\u8389\u82ac</value>
            <value>\u79c0\u6001</value>
            <value>\u9508\u8a00</value>
            <value>\u65ed\u51b2</value>
            <value>\u8f69\u68a6\u98de\u7fd4</value>
            <value>\u96ea\u82b1\u9526\u7ee3(xuehuajinxiu)</value>
            <value>\u96ea\u6676\u5178</value>
            <value>\u96ea\u4e2d\u98de</value>
            <value>\u9e2d\u9e2d</value>
            <value>\u96c5\u6208\u5c14(YOUNGOR)</value>
            <value>\u96c5\u91d1\u5723\u59ae</value>
            <value>\u96c5\u9e7f</value>
            <value>\u5a05\u4e3d\u8fbe</value>
            <value>\u6d0b\u7a3b\u4eba</value>
            <value>\u5996\u7cbe\u7684\u53e3\u888b</value>
            <value>\u8036\u598d</value>
            <value>\u4f0a\u513f\u8d1d\u65af</value>
            <value>\u4f0a\u83f2\u84dd</value>
            <value>\u4f0a\u8299\u4e3d</value>
            <value>\u4f0a\u60c5\u98de\u626c</value>
            <value>\u8863\u54c1\u5929\u6210</value>
            <value>\u8863\u5851\u5bb6(E-artist)</value>
            <value>\u8863\u7f18\u7cfb\u6211</value>
            <value>\u8863\u4e4b\u56fd\u5ea6</value>
            <value>\u4f9d\u5983\u5948\u62c9</value>
            <value>\u4f9d\u5170\u5a07\u5a9a</value>
            <value>\u4f9d\u6f9c\u67ab\u91c7</value>
            <value>\u4f9d\u829d\u5ba3</value>
            <value>\u5b9c\u8212\u5a1c</value>
            <value>\u5f0b\u8bd7\u7d22\u66fc</value>
            <value>\u827a\u6d3e\u4f0a\u4eba</value>
            <value>\u827a\u9014</value>
            <value>\u9038\u5c18\u96c5\u81f4</value>
            <value>\u9038\u9633</value>
            <value>\u9038\u8db3\u98ce</value>
            <value>\u610f\u5c14\u5eb7</value>
            <value>\u610f\u6811(EYENSREE)</value>
            <value>\u8335\u66fc</value>
            <value>\u97f3\u513f</value>
            <value>\u82f1\u4f26\u73ed\u7eb3</value>
            <value>\u6a31\u82b1\u98d8</value>
            <value>\u76c8\u5b89\u82ac</value>
            <value>\u76c8\u96ea\u5170</value>
            <value>\u8424\u6708\u4e3d\u7ec7</value>
            <value>\u4f18\u6770\u4ed5(URSMART)</value>
            <value>\u4f18\u54c1\u539f\u521b</value>
            <value>\u6709\u8863\u6709\u9760(UYUK)</value>
            <value>\u4f51\u742a\u8482\u5a1c</value>
            <value>\u4fde\u5146\u6797(YUZHAOLIN)</value>
            <value>\u4e0e\u72fc\u5171\u821e(DANCING WOLVES)</value>
            <value>\u7389\u7eac</value>
            <value>\u7389\u5e0c</value>
            <value>\u90c1\u9999\u598d</value>
            <value>\u5fa1\u4e50</value>
            <value>\u5143\u59ec</value>
            <value>\u7f18\u672a\u592e</value>
            <value>\u8fdc\u6b65</value>
            <value>\u6708\u6c50</value>
            <value>\u60a6\u6b23\u4e4b\u604b</value>
            <value>\u96f2\u83f2</value>
            <value>\u6218\u5730\u5409\u666e(AFS JEEP)</value>
            <value>\u771f\u7ef4\u65af(Jeanswest)</value>
            <value>\u81fb\u6770\u9f99(JUSTLONG)</value>
            <value>\u6b63\u8863\u5148\u751f</value>
            <value>\u8718\u86db\u738b</value>
            <value>\u667a\u9014</value>
            <value>\u667a\u9014(ZHITU)</value>
            <value>\u7f6e\u8863\u5802(zhiyitang)</value>
            <value>\u7af9\u9999\u97f5\u96c5</value>
            <value>\u5e84\u7235(ZONEJOY)</value>
            <value>\u5353\u723e\u96f7\u767b(ZOERLEIDIN)</value>
            <value>\u5353\u8bd7\u5c3c</value>
            <value>\u5353\u7d2b\u82b1</value>
            <value>\u5353\u7d2b\u8431</value>
            <value>\u5544\u6728\u9e1f</value>
            <value>\u59ff\u6635\u53f6</value>
            <value>\u8d70\u7d22</value>
            <value>\u8db3\u95f4\u821e</value>
            <value>\u5c0a\u9996(ZUNSHOU)</value>
            <value>\u4f50\u4e39\u5974(Giordano)</value>
            <value>\u4f50\u5170\u56fe</value>
        </values>
    </field>
    <field>
        <key>material</key>
        <actions>
            <action>case-insensitive</action>
        </actions>
        <values>
            <value altvalues="\u68c9\u8d28,\u68c9\u5e03,\u68c9\u8d28\u9762\u6599,\u7eaf\u68c9,\u68c9\u4e1d\u5149\u68c9">\u68c9</value>
            <value altvalues="\u83ab\u4ee3\u5c14\u9762\u6599,\u83ab\u4ee3\u5c14\u7ea4\u7ef4,\u83ab\u4ee3\u5c14\u7ea4\u7ef4(\u83ab\u4ee3\u5c14)">\u83ab\u4ee3\u5c14</value>
            <value altvalues="LYCRA\u83b1\u5361">\u83b1\u5361</value>
            <value altvalues="\u5927\u9ebb(\u6c49\u9ebb),\u5927\u9ebb">\u9ebb</value>
            <value altvalues="">\u9ec4\u9ebb</value>
            <value altvalues="">\u7f57\u5e03\u9ebb</value>
            <value altvalues="">\u4e9a\u9ebb</value>
            <value altvalues="">\u82ce\u9ebb</value>
            <value altvalues="">\u9a7c\u6bdb</value>
            <value altvalues="">\u7266\u725b\u6bdb</value>
            <value altvalues="">\u9a6c\u6d77\u6bdb</value>
            <value altvalues="\u6851\u8695\u4e1d,\u67de\u8695\u4e1d">\u8695\u4e1d</value>
            <value altvalues="">\u5154\u6bdb</value>
            <value altvalues="\u5c71\u7f8a\u7ed2(\u7f8a\u7ed2),\u7f8a\u6bdb,\u7f8a\u7f94\u6bdb,\u7f8a\u7ed2,\u7f8a\u7ed2\u5927\u8863\u6599,\u7f8a\u6bdb\u5927\u8863\u6599,\u7f8a\u6bdb/\u7f8a\u7ed2">\u7f8a\u6bdb</value>
            <value altvalues="">\u5b89\u54e5\u62c9\u5c71\u7f8a\u6bdb</value>
            <value altvalues="">\u4eba\u4e1d</value>
            <value altvalues="\u771f\u4e1d\u9762\u6599">\u771f\u4e1d</value>
            <value altvalues="">\u4eff\u771f\u4e1d</value>
            <value altvalues="">\u76ae\u8349</value>
            <value altvalues="">\u76ae\u9769</value>
            <value altvalues="">\u916e\u6c28\u4e1d,\u5bbe\u9738</value>
            <value altvalues="">CVC</value>
            <value altvalues="\u805a\u9170\u80fa\u7ea4\u7ef4(\u9526\u7eb6),\u9526\u7eb6(\u5c3c\u9f99)">\u9526\u7eb6</value>
            <value altvalues="\u805a\u6c28\u916f\u5f39\u6027\u7ea4\u7ef4(\u6c28\u7eb6)">\u6c28\u7eb6</value>
            <value altvalues="\u805a\u4e19\u70ef\u8148\u7ea4\u7ef4(\u8148\u7eb6),\u8148\u7eb6/\u5316\u7ea4">\u8148\u7eb6</value>
            <value altvalues="\u805a\u5bf9\u82ef\u4e8c\u7532\u9178\u4e59\u4e8c\u916f(\u6da4\u7eb6)">\u6da4\u7eb6</value>
            <value altvalues="\u4eba\u68c9,\u9ecf\u80f6">\u9ecf\u80f6\u3001\u4eba\u68c9</value>
            <value altvalues="\u96ea\u7eba\u9762\u6599">\u96ea\u7eba</value>
            <value altvalues="">\u4e54\u5176\u7eb1</value>
            <value altvalues="">\u5854\u4e1d\u9686</value>
            <value altvalues="\u725b\u4ed4\u5e03">\u725b\u4ed4</value>
            <value altvalues="">\u5929\u9e45\u7ed2</value>
            <value altvalues="">\u518d\u751f\u7ea4\u7ef4\u7d20\u7ea4\u7ef4</value>
            <value altvalues="\u65b0\u578b\u805a\u916f\u7ea4\u7ef4,\u805a\u916f">\u805a\u916f\u7ea4\u7ef4</value>
            <value altvalues="">\u6851\u8695\u4e1d</value>
            <value altvalues="">\u7af9\u539f\u7ea4\u7ef4(\u7af9\u7ea4\u7ef4)</value>
            <value altvalues="\u7c98\u80f6\u7ea4\u7ef4(\u7c98\u7ea4)">\u7c98\u80f6\u7ea4\u7ef4</value>
            <value altvalues="\u5c71\u7f8a\u76ae,\u7ef5\u7f8a\u76ae">\u7f8a\u76ae</value>
            <value altvalues="pu\u76ae,PU\u4eba\u9020\u9769">pu</value>
            <value altvalues="\u5176\u5b83,\u5176\u5b83,\u5176\u5b83\u6750\u8d28,\u5176\u5b83\u9762\u6599">\u5176\u4ed6</value>
            <value altvalues="\u5176\u5b83\u5929\u7136\u7ea4\u7ef4">\u5176\u4ed6\u5929\u7136\u7ea4\u7ef4</value>
            <value altvalues="\u5176\u4ed6\u4eba\u9020\u7ea4\u7ef4">\u5176\u4ed6\u5408\u6210\u7ea4\u7ef4</value>
            <value altvalues="\u5c3c\u9f99\u76ae\u9769">\u5c3c\u9f99</value>
            <value altvalues="\u7fbd\u4e1d\u7ed2">\u7fbd\u7ed2</value>
            <value altvalues="\u5370\u82b1\u9762\u6599">\u5370\u82b1</value>
            <value altvalues="\u5176\u5b83\u76ae\u8d28">\u5176\u4ed6\u76ae\u8d28</value>
            <value altvalues="">\u68c9\u7eb6</value>
            <value altvalues="\u6da4\u68c9">\u68c9\u6da4</value>
            <value altvalues="">\u68c9\u6c28</value>
            <value altvalues="">\u918b\u7ea4</value>
            <value altvalues="">\u725b\u6d25\u7eba</value>
            <value altvalues="">\u857e\u4e1d</value>
            <value altvalues="">\u9526\u6da4</value>
            <value altvalues="">\u5316\u7ea4</value>
            <value altvalues="">\u5e73\u7ed2</value>
            <value altvalues="">\u9488\u7ec7\u5e03</value>
            <value altvalues="">\u83b1\u8d5b\u5c14\u7ea4\u7ef4(\u83b1\u8d5b\u5c14)</value>
        </values>
    </field>
    <field>
        <key>color</key>
        <actions>
        </actions>
        <values>
            <value altvalues="\u9f20\u5c3e\u8349\u84dd\u8272,\u7070\u4e01\u5b81\u84dd\u8272,\u77e2\u8f66\u83ca\u84dd\u8272,\u7eff\u677e\u77f3\u84dd\u8272,\u7070\u7eff\u677e\u77f3\u8272,\u4e2d\u7eff\u677e\u77f3\u8272,\u6d45\u6d77\u660c\u84dd\u8272,\u5317\u4eac\u6bdb\u84dd\u8272,\u9053\u5947\u84dd\u8272,\u4eae\u6d77\u84dd\u8272,\u677e\u77f3\u7eff\u8272,\u7389\u77f3\u84dd\u8272,\u6e05\u6c34\u84dd\u8272,\u5b54\u96c0\u7eff\u8272,\u52ff\u5fd8\u8349\u8272,\u6df1\u5929\u84dd\u8272,\u6d77\u6d0b\u84dd\u8272,\u6df1\u7af9\u6708\u8272,\u6df1\u6e56\u84dd\u8272,\u4e2d\u6e56\u84dd\u8272,\u851a\u84dd\u8272,\u7c89\u84dd\u8272,\u6c34\u9e2d\u8272,\u9732\u8349\u8272,\u6c34\u6676\u8272,\u5343\u8349\u8272,\u5929\u84dd\u8272,\u7ed2\u84dd\u8272,\u82cd\u9752\u8272,\u6e56\u84dd\u8272,\u6d45\u7f25\u8272,\u6d77\u7eff\u8272,\u6d77\u84dd\u8272,\u94c1\u84dd\u8272,\u87f9\u9752\u8272,\u975b\u8272,\u6c34\u8272">\u5929\u84dd\u8272</value>
            <value altvalues="\u6d45\u77f3\u677f\u7070\u8272,\u90a3\u74e6\u970d\u767d\u8272,\u7070\u79cb\u9e92\u9e9f\u8272,\u7a3b\u8349\u9ec4\u8272,\u9676\u576f\u9ec4\u8272,\u7389\u7c73\u4e1d\u8272,\u8c61\u7259\u9ec4\u8272,\u67e0\u6aac\u7ef8\u8272,\u5ae9\u59dc\u9ec4\u8272,\u5bcc\u6625\u7eba\u8272,\u7070\u91d1\u83ca\u8272,\u80e1\u7c89\u8272,\u6c99\u6ee9\u8272,\u7c73\u9ec4\u8272,\u4e73\u9ec4\u8272,\u6de1\u7c73\u8272,\u5208\u5b89\u8272,\u8584\u82b1\u8272,\u7eff\u9ec4\u8272,\u674f\u8272,\u6c99\u8272">\u7c73\u9ec4\u8272</value>
            <value altvalues="\u56fd\u9645\u514b\u83b1\u56e0\u84dd\u8272,\u6df1\u5ca9\u6697\u84dd\u7070\u8272,\u677f\u5ca9\u6697\u84dd\u7070\u8272,\u666e\u9c81\u58eb\u84dd\u8272,\u5348\u591c\u84dd\u8272,\u6697\u77ff\u84dd\u8272,\u7687\u519b\u84dd\u8272,\u6df1\u7070\u84dd\u8272,\u6df1\u9752\u83b2\u8272,\u7ec0\u6854\u6897\u8272,\u6697\u6d77\u5170\u8272,\u6c34\u624b\u84dd\u8272,\u95f4\u6697\u84dd\u8272,\u6d77\u519b\u84dd\u8272,\u6e5b\u84dd\u8272,\u54c1\u84dd\u8272,\u84dd\u94c1\u8272,\u519b\u5170\u8272,\u85cf\u9752\u8272,\u975b\u9752\u8272,\u6df1\u5170\u8272,\u7ec0\u84dd\u8272,\u6854\u6897\u8272,\u6697\u9752\u8272,\u6c99\u9752\u8272,\u58a8\u84dd\u8272,\u77ff\u84dd\u8272,\u4e2d\u84dd\u8272,\u975b\u84dd\u8272,\u9edb\u84dd\u8272,\u6d77\u519b\u8272,\u6697\u84dd\u8272,\u6d53\u84dd\u8272,\u85cf\u84dd\u8272,\u7409\u7483\u8272,\u6df1\u84dd\u8272,\u94c1\u7ec0\u8272,\u9edb\u8272,\u7ec0\u8272">\u6df1\u84dd\u8272</value>
            <value altvalues="\u97e6\u5947\u4f0d\u5fb7\u74f7\u84dd\u8272,\u6697\u5a74\u513f\u7c89\u84dd\u8272,\u5a74\u513f\u7c89\u84dd\u8272,\u7231\u4e3d\u4e1d\u84dd\u8272,\u8428\u514b\u65af\u84dd\u8272,\u77f3\u78e8\u84dd\u8272,\u4e2d\u78a7\u84dd\u8272,\u5b54\u96c0\u84dd\u8272,\u95f4\u6d77\u84dd\u8272,\u706b\u836f\u84dd\u8272,\u6d45\u7d2b\u84dd\u8272,\u6d45\u6e56\u84dd\u8272,\u519b\u6821\u84dd\u8272,\u4eae\u5929\u84dd\u8272,\u6697\u7070\u84dd\u8272,\u7c89\u672b\u84dd\u8272,\u51b0\u96ea\u84dd\u8272,\u7409\u7483\u7ec0\u8272,\u519b\u670d\u84dd\u8272,\u4eae\u94a2\u5170\u8272,\u4e2d\u5ca9\u84dd\u8272,\u4eae\u6d77\u7eff\u8272,\u4eae\u94a2\u84dd\u8272,\u6de1\u94a2\u84dd\u8272,\u74ee\u8997\u8272,\u78a7\u84dd\u8272,\u77f3\u84dd\u8272,\u83d8\u84dd\u8272,\u6708\u767d\u8272,\u7af9\u6708\u8272,\u58a8\u7070\u8272,\u84dd\u7070\u8272,\u9752\u84dd\u8272,\u6c34\u84dd\u8272,\u6625\u84dd\u8272,\u6de1\u84dd\u8272,\u6d45\u84dd\u8272,\u94a2\u84dd\u8272,\u7a7a\u8272">\u6d45\u84dd\u8272</value>
            <value altvalues="\u6a44\u6984\u9ed1\u8272,\u767e\u8349\u971c\u8272,\u6cb9\u70df\u58a8\u8272,\u706f\u8349\u7070\u8272,\u4e4c\u8d3c\u58a8\u8272,\u9ed1\u53e4\u94dc\u8272,\u53e4\u94dc\u9ed1\u8272,\u6697\u9ed1\u8272,\u78b3\u9ed1\u8272,\u7164\u9ed1\u8272,\u94c1\u9ed1\u8272,\u70df\u6817\u8272,\u6f06\u9ed1\u8272,\u9ed2\u6a61\u8272,\u9ed2\u7d2b\u8272,\u9752\u9ed1\u8272,\u9edd\u9ed1\u8272,\u571f\u9ed1\u8272,\u7d2b\u9ed2\u8272,\u7eaf\u9ed1\u8272,\u6df1\u9ed1\u8272,\u4e4c\u9ed1\u8272,\u9ed2\u8272,\u9ed1\u8272,\u9edd\u8272,\u9eef\u8272,\u58a8\u8272">\u9ed1\u8272</value>
            <value altvalues="\u9999\u69df\u9ec4\u8272,\u91d1\u9e92\u9e9f\u8272,\u9999\u69df\u8272,\u5e93\u91d1\u8272,\u9ec4\u91d1\u8272,\u91d1\u8272">\u91d1\u8272</value>
            <value altvalues="\u9e20\u7fbd\u9f20\u8272,\u9ec4\u67af\u8336\u8272,\u5361\u5176\u5e03\u8272,\u4eae\u5361\u5176\u8272,\u8461\u8404\u7070\u8272,\u4e39\u4e1c\u77f3\u8272,\u8299\u84c9\u7ea2\u8272,\u6df1\u94f6\u7070\u8272,\u6d45\u5361\u5176\u8272,\u9e7f\u76ae\u978b\u8272,\u4e2d\u68d5\u7070\u8272,\u5361\u5176\u9ec4\u8272,\u6d45\u68d5\u8336\u8272,\u867e\u7070\u8272,\u5976\u6cb9\u8272,\u8089\u68d5\u8272,\u751f\u6210\u8272,\u5361\u5176\u8272,\u9752\u767d\u8272,\u4e73\u68d5\u8272,\u9752\u91d1\u8272,\u679d\u9ec4\u8272,\u9e1f\u5b50\u8272,\u9752\u9ec4\u8272,\u7070\u7c73\u8272,\u9a7c\u7070\u8272,\u874b\u767d\u8272,\u82bd\u7070\u8272,\u7070\u9ec4\u8272,\u674f\u4ec1\u8272,\u4e73\u7070\u8272,\u7c73\u7070\u8272,\u8c61\u7259\u8272,\u9ece\u8272,\u9a7c\u8272">\u6d45\u5361\u5176\u8272</value>
            <value altvalues="\u7d2b\u85e4\u7070\u8272,\u7c97\u6676\u7680\u8272,\u627f\u5fb7\u7070\u8272,\u7c97\u6676\u7682\u8272,\u627f\u5fb3\u7070\u8272,\u82cd\u9ed1\u8272,\u8584\u67ff\u8272,\u6d53\u9f20\u8272,\u9752\u7070\u8272,\u9e4a\u7070\u8272,\u6df1\u7070\u8272,\u94c1\u7070\u8272,\u87f9\u7070\u8272,\u9ed1\u7070\u8272,\u9ed1\u8910\u8272,\u78b3\u7070\u8272,\u94c5\u7070\u8272,\u9ed2\u94c1\u8272,\u9e26\u9752\u8272,\u7070\u8272,\u874b\u8272">\u6df1\u7070\u8272</value>
            <value altvalues="\u82b1\u5349\u767d\u8272,\u53e4\u8463\u767d\u8272,\u8c61\u7259\u767d\u8272,\u7acb\u5fb3\u7c89\u8272,\u674f\u4ec1\u767d\u8272,\u84b2\u516c\u82f1\u8272,\u7389\u77f3\u767d\u8272,\u6d77\u8d1d\u58f3\u8272,\u7f8a\u6bdb\u767d\u8272,\u9c7c\u809a\u767d\u8272,\u767d\u70df\u8272,\u8721\u767d\u8272,\u82b1\u767d\u8272,\u7eaf\u767d\u8272,\u82cd\u767d\u8272,\u96ea\u767d\u8272,\u950c\u767d\u8272,\u837c\u767d\u8272,\u767d\u674f\u8272,\u7cbe\u767d\u8272,\u51c0\u767d\u8272,\u83b9\u767d\u8272,\u6d01\u767d\u8272,\u70df\u767d\u8272,\u6f02\u767d\u8272,\u7d20\u767d\u8272,\u767d\u8272,\u96ea\u8272">\u767d\u8272</value>
            <value altvalues="\u7c97\u5b54\u96c0\u7eff\u8272,\u5e38\u6625\u85e4\u7eff\u8272,\u5b54\u96c0\u77f3\u7eff\u8272,\u67e5\u7279\u9152\u7eff\u8272,\u6df1\u7eff\u5b9d\u77f3\u8272,\u5a01\u5c3c\u65af\u7eff\u8272,\u6df1\u6d77\u6d0b\u7eff\u8272,\u95f4\u7eff\u5b9d\u77f3\u8272,\u7eff\u7409\u7483\u8272,\u82e6\u74dc\u7eff\u8272,\u6a59\u7eff\u4ee5\u8272,\u6d77\u6d0b\u7eff\u8272,\u9752\u74f7\u7eff\u8272,\u94dc\u9508\u7eff\u8272,\u539f\u91ce\u7eff\u8272,\u4e2d\u6625\u7eff\u8272,\u8349\u5730\u7eff\u8272,\u78a7\u7389\u77f3\u8272,\u677e\u67cf\u7eff\u8272,\u67e0\u6aac\u7eff\u8272,\u8349\u576a\u7eff\u8272,\u9178\u6a59\u7eff\u8272,\u4e2d\u6d77\u7eff\u8272,\u871c\u74dc\u7eff\u8272,\u5ae9\u8349\u7eff\u8272,\u5df4\u9ece\u7eff\u8272,\u82d4\u85d3\u7eff\u8272,\u7eff\u5b9d\u77f3\u8272,\u677e\u82b1\u7eff\u8272,\u6df1\u82bd\u7eff\u8272,\u6d0b\u84df\u7eff\u8272,\u9e66\u9e49\u7eff\u8272,\u68ee\u6797\u7eff\u8272,\u9178\u6027\u7eff\u8272,\u6c34\u8349\u7eff\u8272,\u7af9\u9752\u8272,\u6bdb\u7eff\u8272,\u77f3\u7eff\u8272,\u591c\u7eff\u8272,\u7eaf\u7eff\u8272,\u6728\u8d3c\u8272,\u53f6\u7eff\u8272,\u82e5\u7eff\u8272,\u82cd\u7eff\u8272,\u94dc\u7eff\u8272,\u9752\u7fe0\u8272,\u7fe1\u7fe0\u8272,\u95f4\u7eff\u8272,\u4e2d\u7eff\u8272,\u9c9c\u7eff\u8272,\u7389\u7eff\u8272,\u8349\u7eff\u8272,\u679d\u7eff\u8272,\u67f3\u7eff\u8272,\u8471\u7eff\u8272,\u7070\u7eff\u8272,\u7eff\u6c88\u8272,\u78a7\u7eff\u8272,\u8584\u7eff\u8272,\u7eff\u6c89\u8272,\u6df1\u7eff\u8272,\u9752\u7eff\u8272,\u7eff\u7389\u8272,\u5e38\u76d8\u8272,\u94b4\u7eff\u8272,\u5ae9\u7eff\u8272,\u4eae\u7eff\u8272,\u9752\u8471\u8272,\u660e\u7eff\u8272,\u94ec\u7eff\u8272,\u8001\u7eff\u8272,\u65b0\u82bd\u8272,\u9752\u78a7\u8272,\u82cd\u7fe0\u8272,\u6625\u7eff\u8272,\u6cb9\u7eff\u8272,\u9549\u7eff\u8272,\u7eff\u8272,\u8349\u8272,\u67f3\u8272,\u74dc\u8272,\u82d4\u8272">\u7eff\u8272</value>
            <value altvalues="\u4ed9\u658e\u8336\u8272,\u8c61\u7259\u9ed1\u8272,\u6c34\u8c82\u7070\u8272,\u6d45\u83b2\u7070\u8272,\u5229\u4f11\u9f20\u8272,\u5361\u5176\u7070\u8272,\u4e2d\u7070\u5170\u8272,\u627f\u5fb7\u7682\u8272,\u6c34\u6ce5\u7070\u8272,\u4eae\u5ca9\u7070\u8272,\u6df1\u74e6\u7070\u8272,\u7ec7\u9526\u7070\u8272,\u77f3\u677f\u7070\u8272,\u70df\u7070\u8272,\u84dd\u9f20\u8272,\u4e2d\u7070\u8272,\u94f6\u7b94\u8272,\u94f6\u9f20\u8272,\u8c46\u7070\u8272,\u6697\u7070\u8272,\u679c\u7070\u8272,\u8001\u94f6\u8272,\u8584\u9f20\u8272,\u5929\u7070\u8272,\u7070\u84dd\u8272,\u8584\u949d\u8272,\u9f20\u7070\u8272,\u85d5\u7070\u8272,\u6b63\u7070\u8272,\u5ca9\u7070\u8272,\u660f\u7070\u8272,\u8584\u58a8\u8272,\u94c1\u8272">\u4e2d\u7070\u8272</value>
            <value altvalues="\u6d45\u79cb\u9e92\u9e9f\u9ec4\u8272,\u67e0\u6aac\u8584\u7eb1\u8272,\u4e1d\u74dc\u82b1\u9ec4\u8272,\u542b\u7f9e\u8349\u9ec4\u8272,\u5c0f\u9e21\u9ec4\u8272,\u9e2d\u5375\u9752\u8272,\u5411\u65e5\u8475\u8272,\u79cb\u9e92\u9e9f\u8272,\u6d45\u6854\u9ec4\u8272,\u82a5\u672b\u9ec4\u8272,\u6a44\u6984\u9ec4\u8272,\u4eae\u91d1\u9ec4\u8272,\u6a31\u8349\u9ec4\u8272,\u67e0\u6aac\u9ec4\u8272,\u8309\u8389\u9ec4\u8272,\u8349\u9ec4\u8272,\u8273\u9ec4\u8272,\u91d1\u9ec4\u8272,\u9ec4\u6a97\u8272,\u867e\u9ec4\u8272,\u7259\u7eff\u8272,\u6a31\u8349\u8272,\u6d45\u9ec4\u8272,\u9e2d\u9ec4\u8272,\u9ec4\u94dc\u8272,\u4eae\u9ec4\u8272,\u5ae9\u9ec4\u8272,\u6de1\u9ec4\u8272,\u9c9c\u9ec4\u8272,\u9e45\u9ec4\u8272,\u7eaf\u9ec4\u8272,\u9db8\u8272,\u7259\u8272,\u7f03\u8272,\u9ec4\u8272,\u7f1f\u8272,\u9999\u8272">\u6d45\u9ec4\u8272</value>
            <value altvalues="\u94f6\u661f\u6d77\u68e0\u8272,\u4e4c\u7f57\u677e\u7ea2\u8272,\u7d2b\u7f57\u5170\u7ea2\u8272,\u8910\u73ab\u7470\u7ea2\u8272,\u739b\u7459\u7ea2\u8272,\u77f3\u69b4\u7ea2\u8272,\u6708\u5b63\u7ea2\u8272,\u80ed\u8102\u7ea2\u8272,\u69b4\u82b1\u7ea2\u8272,\u7ea2\u5b9d\u77f3\u8272,\u8543\u8304\u7ea2\u8272,\u6cd5\u56fd\u7ea2\u8272,\u73ab\u7470\u7ea2\u8272,\u5c71\u8336\u7ea2\u8272,\u6a31\u6843\u7ea2\u8272,\u897f\u7ea2\u67ff\u8272,\u756a\u8304\u7ea2\u8272,\u8840\u7259\u7ea2\u8272,\u9c91\u9c7c\u7ea2\u8272,\u7261\u4e39\u7ea2\u8272,\u6d45\u82cf\u82b3\u8272,\u5b9d\u77f3\u7ea2\u8272,\u8fa3\u6912\u7ea2\u8272,\u8c61\u7259\u7ea2\u8272,\u7eaf\u7ea2\u8272,\u6d45\u7ea2\u8272,\u82cf\u82b3\u8272,\u5983\u7ea2\u8272,\u7ea2\u6885\u8272,\u82f9\u679c\u8272,\u8089\u7ea2\u8272,\u8165\u7ea2\u8272,\u9549\u7ea2\u8272,\u9c9c\u7ea2\u8272,\u5747\u7ea2\u8272,\u4eca\u6837\u8272,\u6bb7\u7ea2\u8272,\u706b\u7ea2\u8272,\u8fb0\u6c99\u8272,\u7ea2\u8d64\u8272,\u6a31\u6843\u8272,\u5ae3\u7ea2\u8272,\u6de1\u7ea2\u8272,\u756a\u8304\u8272,\u771f\u7ea2\u8272,\u7261\u4e39\u8272,\u9161\u7ea2\u8272,\u8d64\u9516\u8272,\u7329\u7ea2\u8272,\u8840\u7ea2\u8272,\u7ae0\u4e39\u8272,\u66d9\u7ea2\u8272,\u5927\u7ea2\u8272,\u7eef\u7ea2\u8272,\u8d6d\u8272,\u831c\u8272,\u7ea2\u8272,\u8d6b\u8272,\u5f64\u8272,\u708e\u8272,\u8d64\u8272,\u7eef\u8272,\u6731\u8272">\u7ea2\u8272</value>
            <value altvalues="\u7518\u8349\u9ec4\u8272,\u7389\u7c73\u9ec4\u8272,\u756a\u6728\u74dc\u8272,\u6697\u91d1\u83ca\u8272,\u8010\u706b\u7816\u8272,\u9ec4\u7409\u7483\u8272,\u8def\u8003\u8336\u8272,\u82cd\u9e92\u9e9f\u8272,\u91d1\u68d5\u8272,\u59dc\u9ec4\u8272,\u77f3\u9ec4\u8272,\u7389\u7c73\u8272,\u94b4\u9ec4\u8272,\u7259\u9ec4\u8272,\u86cb\u9ec4\u8272,\u6df1\u9ec4\u8272,\u91d1\u8336\u8272,\u9549\u9ec4\u8272,\u69d0\u9ec4\u8272,\u8d64\u91d1\u8272,\u8702\u871c\u8272,\u6708\u9ec4\u8272,\u7802\u9ec4\u8272,\u9ec4\u571f\u8272,\u840c\u9ec4\u8272,\u6c34\u9ec4\u8272,\u79cb\u9999\u8272,\u8431\u8349\u8272,\u4e2d\u9ec4\u8272,\u8471\u9ec4\u8272,\u660f\u9ec4\u8272,\u82cd\u9ec4\u8272,\u67af\u9ec4\u8272,\u660e\u9ec4\u8272,\u9974\u8272,\u5375\u8272,\u6cb9\u8272,\u67af\u8272">\u4e2d\u9ec4\u8272</value>
            <value altvalues="\u4e07\u5bff\u83ca\u9ec4\u8272,\u4eae\u91d1\u83ca\u9ec4\u8272,\u5357\u74dc\u9ec4\u8272,\u6697\u91d1\u9ec4\u8272,\u6df1\u6854\u9ec4\u8272,\u6697\u6854\u9ec4\u8272,\u65e5\u5149\u9ec4\u8272,\u70ed\u5e26\u6a59\u8272,\u571f\u5668\u8272,\u6854\u9ec4\u8272,\u91d1\u8d64\u8272,\u90c1\u91d1\u8272,\u9ec4\u8d64\u8272,\u9633\u6a59\u8272,\u6a58\u9ec4\u8272,\u6a59\u9ec4\u8272,\u94c1\u9ec4\u8272,\u6d45\u6a59\u8272,\u5c71\u5439\u8272,\u96c4\u9ec4\u8272,\u67d1\u5b50\u8272,\u94ec\u9ec4\u8272,\u571f\u9ec4\u8272,\u6697\u9ec4\u8272,\u7c89\u6a59\u8272,\u85e4\u9ec4\u8272,\u7425\u73c0\u8272,\u674f\u9ec4\u8272,\u8001\u82b1\u8272,\u91d1\u83ca\u8272,\u6842\u76ae\u8272,\u82a6\u9ec4\u8272,\u6854\u8272,\u6a58\u8272,\u72d0\u8272,\u571f\u8272,\u6a59\u8272">\u6a58\u9ec4\u8272</value>
            <value altvalues="\u56fd\u9645\u5947\u8fde\u84dd\u8272,\u5929\u9752\u77f3\u84dd\u8272,\u6781\u6d53\u6d77\u84dd\u8272,\u6708\u5149\u84dd\u8272,\u58eb\u6797\u84dd\u8272,\u84dd\u5b9d\u77f3\u8272,\u5b9d\u77f3\u84dd\u8272,\u5317\u4eac\u84dd\u8272,\u7687\u5bb6\u84dd\u8272,\u9c9c\u84dd\u8272,\u5b9d\u84dd\u8272,\u7eaf\u84dd\u8272,\u95ea\u5170\u8272,\u94b4\u84dd\u8272,\u7fa4\u9752\u8272,\u4eae\u84dd\u8272,\u5f69\u84dd\u8272,\u84dd\u8272,\u5170\u8272">\u84dd\u8272</value>
            <value altvalues="\u9ec4\u571f\u8d6d\u8272,\u4e9a\u9ebb\u5e03\u8272,\u9a6c\u978d\u68d5\u8272,\u4e01\u5b50\u8336\u8272,\u6d45\u9ec4\u68d5\u8272,\u9cdd\u9c7c\u9ec4\u8272,\u6d45\u8910\u8272,\u65e5\u6652\u8272,\u6de1\u8910\u8272,\u6d45\u68d5\u8272,\u9a86\u9a7c\u8272,\u4e2d\u9a7c\u8272,\u6a59\u8910\u8272,\u68d5\u9ec4\u8272,\u4e4c\u91d1\u8272,\u4e01\u5b50\u8272,\u7d2b\u94dc\u8272,\u4e9a\u9ebb\u8272,\u6c99\u68d5\u8272,\u53e4\u91d1\u8272,\u9ec4\u68d5\u8272,\u786c\u6728\u8272,\u68d5\u8336\u8272,\u9ec4\u6a61\u8272,\u5c0f\u9ea6\u8272,\u7126\u9999\u8272,\u7ea2\u72d0\u8272,\u82a5\u5b50\u8272,\u6a80\u9999\u8272,\u571f\u7070\u8272,\u7eb8\u68d5\u8272,\u9ec4\u8910\u8272,\u7070\u571f\u8272,\u6728\u8272">\u6d45\u68d5\u8272</value>
            <value altvalues="\u6df1\u77f3\u677f\u7070\u8272,\u6697\u5b9d\u77f3\u7eff\u8272,\u84dd\u6d77\u677e\u8336\u8272,\u6697\u6a44\u6984\u7eff\u8272,\u94c1\u5fa1\u7eb3\u6237\u8272,\u6697\u5ca9\u7070\u8272,\u9752\u767d\u6a61\u8272,\u6df1\u7eff\u8910\u8272,\u6de1\u7070\u7eff\u8272,\u6697\u82d4\u7eff\u8272,\u58a8\u7389\u7eff\u8272,\u5fa1\u7eb3\u6237\u8272,\u6697\u6d77\u7eff\u8272,\u6df1\u7fe0\u7eff\u8272,\u5343\u6b73\u7eff\u8272,\u6df1\u677e\u7eff\u8272,\u7070\u6e56\u7eff\u8272,\u9516\u9f20\u8272,\u8336\u7eff\u8272,\u840c\u8471\u8272,\u6697\u7eff\u8272,\u7fe0\u7eff\u8272,\u9244\u7eff\u8272,\u82d4\u7070\u8272,\u51eb\u7eff\u8272,\u9edb\u7eff\u8272,\u58a8\u7eff\u8272,\u8584\u7f25\u8272,\u9eb9\u5c18\u8272,\u8910\u8fd4\u8272">\u58a8\u7eff\u8272</value>
            <value altvalues="\u6d45\u77f3\u82f1\u7d2b\u8272,\u6d45\u7070\u7d2b\u7ea2\u8272,\u85b0\u8863\u8349\u7d2b\u8272,\u6d45\u51e4\u4ed9\u7d2b\u8272,\u73ab\u7470\u7d2b\u7ea2\u8272,\u6de1\u7d2b\u4e01\u9999\u8272,\u4e09\u8272\u5807\u7d2b\u8272,\u94c1\u7ebf\u83b2\u7d2b\u8272,\u7d2b\u6c34\u6676\u8272,\u53e4\u4ee3\u7d2b\u8272,\u5170\u82b1\u7d2b\u8272,\u7d2b\u4e01\u9999\u8272,\u7d2b\u7f57\u5170\u8272,\u8304\u76ae\u7d2b\u8272,\u73ab\u7470\u7d2b\u8272,\u6728\u69ff\u7d2b\u8272,\u8461\u8404\u9f20\u8272,\u7275\u725b\u7d2b\u8272,\u4e01\u9999\u7d2b\u8272,\u85e4\u7eb3\u6237\u8272,\u6697\u5170\u7d2b\u8272,\u9752\u83b2\u7d2b\u8272,\u4e2d\u5170\u7d2b\u8272,\u6df1\u7d2b\u7ea2\u8272,\u4e2d\u7d2b\u7ea2\u8272,\u6697\u6d0b\u7ea2\u8272,\u96ea\u9752\u7070\u8272,\u7d2b\u8587\u82b1\u8272,\u6d45\u85e4\u7d2b\u8272,\u7ea2\u7d2b\u8272,\u9e20\u7fbd\u8272,\u6d45\u7d2b\u8272,\u85d5\u8377\u8272,\u85e4\u7d2b\u8272,\u7d2b\u85e4\u8272,\u9c9c\u7d2b\u8272,\u6de1\u7d2b\u8272,\u9171\u7d2b\u8272,\u5170\u7d2b\u8272,\u5ca9\u84dd\u8272,\u675c\u82e5\u8272,\u7d2b\u9171\u8272,\u4e4c\u7d2b\u8272,\u4e8c\u84dd\u8272,\u94b4\u7d2b\u8272,\u9752\u83b2\u8272,\u77ff\u7d2b\u8272,\u96ea\u9752\u8272,\u4e01\u9999\u8272,\u6d0b\u674e\u8272,\u84df\u7d2b\u8272,\u9752\u7d2b\u8272,\u674e\u7d2b\u8272,\u96ea\u7d2b\u8272,\u8461\u8404\u8272,\u7d2b\u68e0\u8272,\u4eae\u7d2b\u8272,\u83eb\u8272,\u7d2b\u8272,\u80dc\u8272,\u4e4c\u8272,\u85e4\u8272">\u7d2b\u8272</value>
            <value altvalues="\u5176\u5b83\u8272,\u5176\u4ed6\u8272">\u5176\u4ed6</value>
            <value altvalues="\u6697\u7eff\u677e\u77f3\u8272,\u7eff\u677e\u77f3\u7eff\u8272,\u4e2d\u6761\u867e\u7eff\u8272,\u6c34\u6676\u7eff\u8272,\u51ac\u74dc\u7eff\u8272,\u5c06\u6821\u5462\u8272,\u6a44\u6984\u7eff\u8272,\u5927\u8d64\u91d1\u8272,\u6df1\u8349\u7eff\u8272,\u5361\u5176\u7eff\u8272,\u8910\u7eff\u8272,\u9db8\u8336\u8272,\u519b\u7eff\u8272,\u56fd\u9632\u8272,\u68d5\u7eff\u8272,\u677e\u53f6\u8272,\u9752\u4e39\u8272,\u4f3d\u7f57\u8272,\u6a44\u6984\u8272,\u6d77\u677e\u8272,\u83ba\u8336\u8272,\u677e\u7eff\u8272,\u51ac\u7eff\u8272,\u62b9\u8336\u8272,\u5c71\u9e20\u8272,\u83ba\u8272">\u519b\u7eff\u8272</value>
            <value altvalues="\u5a01\u5c3c\u65af\u7ea2\u8272,\u7ea2\u6d77\u8001\u8336\u8272,\u5370\u7b2c\u5b89\u7ea2\u8272,\u9e21\u51a0\u82b1\u7ea2\u8272,\u8010\u706b\u7816\u7ea2\u8272,\u94c1\u9508\u7ea2\u8272,\u6d77\u87ba\u7ea2\u8272,\u6697\u7edb\u7ea2\u8272,\u73b3\u7441\u7ea2\u8272,\u6df1\u70df\u7ea2\u8272,\u6df1\u91c9\u7ea2\u8272,\u58a8\u7edb\u7ea2\u8272,\u90ce\u7a91\u7ea2\u8272,\u9ad8\u7cb1\u7ea2\u8272,\u8c49\u8c46\u7ea2\u8272,\u91c9\u5e95\u7ea2\u8272,\u706b\u7816\u8272,\u706d\u7d2b\u8272,\u67a3\u7ea2\u8272,\u8d6b\u8d64\u8272,\u6697\u7ea2\u8272,\u6df1\u7ea2\u8272,\u80ed\u8102\u8272,\u8549\u7ea2\u8272,\u54c1\u7ea2\u8272,\u6d0b\u7ea2\u8272,\u5f01\u67c4\u8272,\u80e1\u6843\u8272,\u7816\u7ea2\u8272,\u9508\u7ea2\u8272,\u7d2b\u6a80\u8272,\u8d6d\u77f3\u8272,\u94c1\u7ea2\u8272,\u6731\u7802\u8272,\u4e8c\u6731\u8272,\u571f\u7ea2\u8272,\u5c0f\u8c46\u8272,\u9152\u7ea2\u8272,\u685c\u8272">\u6df1\u7ea2\u8272</value>
            <value altvalues="\u94f6\u7070\u8272,\u8336\u9f20\u8272,\u94f6\u767d\u8272,\u94f6\u8272,\u950c\u8272">\u94f6\u8272</value>
            <value altvalues="\u5e9a\u65af\u535a\u7f57\u7070\u8272,\u4eae\u84dd\u7070\u8272,\u6d45\u7c73\u7070\u8272,\u7eb3\u74e6\u767d\u8272,\u950c\u94a1\u767d\u8272,\u7261\u86ce\u767d\u8272,\u73cd\u73e0\u767d\u8272,\u5e7d\u7075\u767d\u8272,\u6d45\u68d5\u7070\u8272,\u9e3d\u5b50\u7070\u8272,\u9e7f\u76ae\u8272,\u7c89\u68d5\u8272,\u96ea\u7070\u8272,\u7c73\u7ef8\u8272,\u7070\u767d\u8272,\u7c73\u767d\u8272,\u6de1\u7070\u8272,\u6930\u8910\u8272,\u7070\u77f3\u8272,\u4eae\u7070\u8272,\u6d45\u7070\u8272,\u672c\u767d\u8272,\u767d\u7070\u8272,\u94c5\u767d\u8272,\u96fe\u7070\u8272,\u4e73\u767d\u8272,\u673d\u53f6\u8272,\u82b1\u7070\u8272,\u7c73\u8272,\u7efe\u8272,\u6bdb\u8272,\u9ebb\u8272,\u8584\u8272,\u7802\u8272,\u79d8\u8272,\u7d20\u8272,\u77f3\u8272,\u971c\u8272,\u9f20\u8272">\u6d45\u7070\u8272</value>
            <value altvalues="\u6cd5\u56fd\u68a7\u6850\u76ae\u8272,\u6a44\u6984\u519b\u670d\u7eff\u8272,\u7a7a\u4e94\u500d\u5b50\u8272,\u6df1\u5361\u5176\u5e03\u8272,\u5ead\u9662\u74e6\u7070\u8272,\u6a44\u6984\u571f\u8910\u8272,\u7f57\u6c49\u679c\u8272,\u76f8\u601d\u7070\u8272,\u73c8\u7432\u68d5\u8272,\u6a44\u6984\u7070\u8272,\u6697\u5361\u5176\u8272,\u6d45\u7070\u8910\u8272,\u6df1\u5361\u5176\u8272,\u6728\u5170\u8272,\u9ec4\u680c\u8272,\u9752\u8910\u8272,\u5a9a\u8336\u8272,\u7070\u8910\u8272,\u4e9c\u9ebb\u8272,\u67af\u8336\u8272,\u751f\u58c1\u8272,\u756a\u6728\u8272,\u6c99\u8910\u8272,\u571f\u8910\u8272,\u9516\u8272,\u79cb\u8272,\u9ee7\u8272,\u6d85\u8272,\u94c5\u8272,\u9769\u8272">\u6df1\u5361\u5176\u8272</value>
            <value altvalues="\u9f99\u6cc9\u9752\u74f7\u91c9\u8272,\u4eae\u67e0\u6aac\u7eff\u8272,\u6d45\u6d77\u6d0b\u7eff\u8272,\u8584\u8377\u5976\u6cb9\u8272,\u82cd\u5b9d\u77f3\u7eff\u8272,\u6d45\u6c34\u7eff\u8272,\u8377\u830e\u7eff\u8272,\u6d45\u677e\u7eff\u8272,\u6d45\u7eff\u7070\u8272,\u6d45\u8349\u7eff\u8272,\u6c34\u6d45\u8471\u8272,\u6d45\u8c46\u6c99\u8272,\u6d45\u8c46\u7eff\u8272,\u9516\u6d45\u8471\u8272,\u5929\u6c34\u78a7\u8272,\u9752\u53e4\u94dc\u8272,\u82f9\u679c\u7eff\u8272,\u5ae9\u8471\u7eff\u8272,\u6d45\u9c9c\u7eff\u8272,\u6d77\u6c34\u7eff\u8272,\u87f9\u58f3\u9752\u8272,\u9752\u867e\u8272,\u8c46\u7eff\u8272,\u827e\u7eff\u8272,\u9ec4\u7070\u8272,\u9752\u7af9\u8272,\u6768\u6843\u8272,\u9508\u7eff\u8272,\u82e5\u8349\u8272,\u7eff\u9ec4\u8272,\u67f3\u9ec4\u8272,\u9752\u8c46\u8272,\u9752\u7eff\u8272,\u767d\u7eff\u8272,\u8471\u5029\u8272,\u679c\u7eff\u8272,\u5976\u7eff\u8272,\u5143\u9752\u8272,\u82e5\u7af9\u8272,\u9178\u6a59\u8272,\u67af\u7eff\u8272,\u77f3\u9752\u8272,\u677e\u82b1\u8272,\u82a5\u672b\u8272,\u6de1\u7eff\u8272,\u82a6\u7070\u8272,\u6d45\u7eff\u8272,\u5229\u4e45\u8272,\u4e09\u7eff\u8272,\u6c99\u7eff\u8272,\u54c1\u7eff\u8272,\u6c34\u7eff\u8272,\u9ec4\u7eff\u8272,\u7389\u8272,\u82cd\u8272,\u7f25\u8272,\u82d7\u8272">\u6d45\u7eff\u8272</value>
            <value altvalues="\u6d45\u9752\u74f7\u91c9\u8272,\u95f4\u6625\u7eff\u8272,\u9e2d\u86cb\u9752\u8272,\u8584\u8377\u7eff\u8272,\u7eff\u677e\u77f3\u8272,\u6de1\u9752\u8272,\u9edb\u9752\u8272,\u7c89\u9752\u8272,\u7ec0\u9752\u8272,\u94a2\u9752\u8272,\u7eff\u84dd\u8272,\u6e56\u7eff\u8272,\u65b0\u6865\u8272,\u5927\u9752\u8272,\u8584\u8377\u8272,\u6d45\u9752\u8272,\u86cb\u9752\u8272,\u6df1\u9752\u8272,\u767d\u7fa4\u8272,\u8471\u9752\u8272,\u94c1\u9752\u8272,\u9c9c\u9752\u8272,\u7eff\u9752\u8272,\u83ca\u5170\u8272,\u94a2\u5170\u8272,\u5929\u9752\u8272,\u5f71\u9752\u8272,\u8c46\u9752\u8272,\u4eae\u9752\u8272,\u84dd\u7eff\u8272,\u82b1\u9752\u8272,\u6d45\u8471\u8272,\u9752\u78c1\u8272,\u9701\u9752\u8272,\u9752\u8272,\u78a7\u8272">\u9752\u8272</value>
            <value altvalues="\u73ab\u7470\u8910\u8272,\u6d77\u8001\u8336\u8272,\u9e7f\u76ae\u68d5\u8272,\u5de7\u53ef\u529b\u8272,\u9cdd\u9c7c\u9752\u8272,\u5de7\u514b\u529b\u8272,\u978d\u8910\u8272,\u79d8\u9c81\u8272,\u7164\u7af9\u8272,\u8336\u9752\u8272,\u6867\u76ae\u8272,\u5496\u5561\u8272,\u9ec4\u8336\u8272,\u68d5\u8910\u8272,\u5b9e\u6728\u8272,\u7070\u8336\u8272,\u68d5\u7ea2\u8272,\u8336\u8910\u8272,\u53e4\u94dc\u8272,\u6817\u8910\u8272,\u6652\u9ed1\u8272,\u7c9f\u8272,\u6817\u8272,\u8910\u8272,\u68d5\u8272">\u8910\u8272</value>
            <value altvalues="\u82cd\u7d2b\u7f57\u5170\u8272,\u6df1\u5170\u82b1\u7d2b\u8272,\u6697\u7d2b\u7f57\u5170\u8272,\u6df1\u7d2b\u7f57\u5170\u8272,\u67cf\u574a\u7070\u84dd\u8272,\u9f99\u80c6\u7d2b\u8272,\u6697\u5ca9\u84dd\u8272,\u7d2b\u7f57\u84dd\u8272,\u8461\u8404\u7d2b\u8272,\u6df1\u7d2b\u7070\u8272,\u9edb\u87ba\u8272,\u58a8\u7d2b\u8272,\u7ec0\u7d2b\u8272,\u84dd\u7d2b\u8272,\u7d2b\u7ec0\u8272,\u7d2b\u7070\u8272,\u7384\u9752\u8272,\u8d64\u7d2b\u8272,\u6df1\u7d2b\u8272,\u7d2b\u84dd\u8272,\u9752\u949d\u8272,\u9edb\u7d2b\u8272,\u6697\u7d2b\u8272">\u6df1\u7d2b\u8272</value>
            <value altvalues="\u6d45\u7edb\u7ea2\u8272,\u6697\u9c91\u7ea2\u8272,\u5370\u5ea6\u7ea2\u8272,\u67ff\u5b50\u6a59\u8272,\u7ea2\u6247\u8d1d\u8272,\u70ed\u7c89\u7ea2\u8272,\u4eae\u9c91\u7ea2\u8272,\u73ca\u745a\u7ea2\u8272,\u6de1\u73ca\u745a\u8272,\u7ea2\u6a59\u8272,\u6697\u6a59\u8272,\u82cf\u6728\u8272,\u91c9\u7ea2\u8272,\u94ec\u7ea2\u8272,\u6df1\u6a59\u8272,\u6854\u68d5\u8272,\u67ff\u5b50\u8272,\u6800\u5b50\u8272,\u4ee3\u8d6d\u8272,\u6a58\u7ea2\u8272,\u94c1\u9508\u8272,\u871c\u6a59\u8272,\u9161\u989c\u8272,\u674f\u7ea2\u8272,\u6854\u7ea2\u8272,\u6731\u8198\u8272,\u8d64\u6a59\u8272,\u6a59\u7ea2\u8272,\u96c4\u7cbe\u8272,\u94f6\u6731\u8272,\u6cb9\u7ea2\u8272,\u8fb0\u7802\u8272,\u871c\u67d1\u8272,\u70bc\u74e6\u8272,\u9c91\u7ea2\u8272,\u739b\u7459\u8272,\u6768\u5983\u8272,\u7ea2\u7682\u8272,\u6731\u7ea2\u8272,\u771f\u8d6d\u8272,\u7ea2\u6866\u8272,\u94c5\u4e39\u8272,\u831c\u7ea2\u8272,\u8d64\u8910\u8272,\u9ec4\u4e39\u8272,\u6d17\u6731\u8272,\u71c3\u6a59\u8272,\u91d1\u7ea2\u8272,\u73ca\u745a\u8272,\u66d9\u8272,\u6a80\u8272,\u4e39\u8272,\u5983\u8272,\u6866\u8272,\u67ff\u8272">\u6a59\u7ea2\u8272</value>
            <value altvalues="\u8309\u8389\u82b1\u7ea2\u8272,\u4f18\u54c1\u7d2b\u7ea2\u8272,\u4e2d\u9752\u7d2b\u7ea2\u8272,\u6d0b\u73ab\u7470\u7ea2\u8272,\u6d45\u73ab\u7470\u7ea2\u8272,\u6df1\u6d0b\u7ea2\u8272,\u7d2b\u6247\u8d1d\u8272,\u6de1\u7d2b\u7ea2\u8272,\u4eae\u7c89\u7ea2\u8272,\u7f2c\u8349\u7d2b\u8272,\u6d45\u83b2\u7ea2\u8272,\u73ab\u7470\u7070\u8272,\u6df1\u85d5\u7ea2\u8272,\u6696\u7c89\u7ea2\u8272,\u7ea2\u7070\u83b2\u8272,\u9526\u8475\u7d2b\u8272,\u67a2\u673a\u7ea2\u8272,\u6d77\u68e0\u7ea2\u8272,\u6d0b\u8471\u7d2b\u8272,\u7ea2\u83b2\u7070\u8272,\u6843\u7ea2\u8272,\u73ab\u7ea2\u8272,\u8273\u7c89\u8272,\u7d2b\u7c89\u8272,\u77f3\u7af9\u8272,\u7edb\u7d2b\u8272,\u67a3\u7d2b\u8272,\u7d2b\u7ea2\u8272,\u6df1\u7c89\u8272,\u674e\u5b50\u8272,\u8e2f\u8e85\u8272,\u7d2b\u7edb\u8272,\u6c34\u7ea2\u8272,\u6885\u7ea2\u8272,\u8d64\u4e39\u8272,\u8d6d\u7ea2\u8272,\u7ea2\u7eef\u8272,\u94f6\u7ea2\u8272,\u8336\u8272">\u73ab\u7ea2\u8272</value>
            <value altvalues="\u85b0\u8863\u8349\u7d2b\u7ea2\u8272,\u5c16\u6676\u77f3\u7ea2\u8272,\u6d45\u73cd\u73e0\u7ea2\u8272,\u6d45\u73ca\u745a\u7ea2\u8272,\u8584\u96fe\u73ab\u7470\u8272,\u58f3\u9ec4\u7ea2\u8272,\u6de1\u7d2b\u767d\u8272,\u739b\u7459\u7c89\u8272,\u6de1\u7d2b\u7070\u8272,\u6d45\u7c89\u7ea2\u8272,\u7c89\u7ea2\u767d\u8272,\u8377\u82b1\u7ea2\u8272,\u6d45\u9c9c\u8089\u8272,\u6d45\u8840\u7259\u8272,\u8089\u68d5\u7070\u8272,\u7c89\u6251\u6843\u8272,\u706b\u9e64\u7ea2\u8272,\u7518\u77f3\u7c89\u8272,\u7070\u7d2b\u7ea2\u8272,\u6df1\u9c9c\u8089\u8272,\u6d45\u9c91\u7ea2\u8272,\u6de1\u85d5\u5408\u8272,\u7c89\u51e4\u4ed9\u8272,\u957f\u6625\u82b1\u8272,\u4eae\u73ca\u745a\u8272,\u5341\u6837\u9526\u8272,\u51e4\u4ed9\u7c89\u8272,\u6de1\u767d\u7d2b\u8272,\u6d45\u8089\u7c89\u8272,\u96fe\u73ab\u7470\u8272,\u8d64\u767d\u6a61\u8272,\u86e4\u870a\u7c89\u8272,\u6df1\u7c89\u7ea2\u8272,\u6c5f\u6237\u7d2b\u8272,\u6d45\u73ab\u7470\u8272,\u8584\u7ea2\u6885\u8272,\u65e7\u857e\u4e1d\u8272,\u8089\u9ec4\u8272,\u6697\u7c89\u8272,\u6d17\u67ff\u8272,\u8089\u7c89\u8272,\u4eae\u8089\u8272,\u6de1\u7c89\u8272,\u9c9c\u8089\u8272,\u6d45\u7c89\u8272,\u8c46\u6c99\u8272,\u6697\u8089\u8272,\u8089\u6842\u8272,\u83b2\u7ea2\u8272,\u767d\u7c89\u8272,\u7c89\u7ea2\u8272,\u8537\u8587\u8272,\u7c89\u767d\u8272,\u5976\u68d5\u8272,\u83b2\u7070\u8272,\u9000\u7ea2\u8272,\u6d77\u8d1d\u8272,\u83d6\u84b2\u8272,\u6e58\u5983\u8272,\u7c73\u7ea2\u8272,\u86e4\u7c89\u8272,\u6d45\u9a7c\u8272,\u88f8\u80a4\u8272,\u9e28\u8272,\u4eba\u8272,\u84df\u8272,\u6843\u8272,\u8089\u8272,\u7c89\u8272,\u808c\u8272,\u871c\u8272,\u85d5\u8272">\u7c89\u7ea2\u8272</value>
            <value altvalues="\u52c3\u826e\u7b2c\u9152\u7ea2\u8272,\u73ab\u7470\u68d5\u8272,\u6697\u6df1\u7ea2\u8272,\u6697\u9ec4\u8910\u8272,\u8304\u5b50\u7ec0\u8272,\u6a44\u6984\u68d5\u8272,\u6731\u53e4\u529b\u8272,\u94f6\u7164\u7af9\u8272,\u94c1\u9508\u68d5\u8272,\u6df1\u7eef\u8272,\u91cd\u8910\u8272,\u7ea2\u68d5\u8272,\u8349\u7070\u8272,\u6817\u6885\u8272,\u8c46\u68d5\u8272,\u8d64\u8336\u8272,\u7d2b\u8910\u8272,\u8d64\u94dc\u8272,\u6df1\u6817\u8272,\u6df1\u70df\u8272,\u68d5\u9ed1\u8272,\u9ed2\u8336\u8272,\u7126\u8336\u8272,\u6866\u8336\u8272,\u6697\u8910\u8272,\u6df1\u8910\u8272,\u91a4\u8272,\u7f01\u8272,\u9e22\u8272,\u7384\u8272,\u9171\u8272">\u6df1\u8910\u8272</value>
            <value altvalues="\u7070\u7eff\u677e\u77f3,\u77e2\u8f66\u83ca\u84dd,\u9f20\u5c3e\u8349\u84dd,\u6d45\u6d77\u660c\u84dd,\u7070\u4e01\u5b81\u84dd,\u4e2d\u7eff\u677e\u77f3,\u7eff\u677e\u77f3\u84dd,\u5317\u4eac\u6bdb\u84dd,\u5b54\u96c0\u7eff,\u9053\u5947\u84dd,\u6df1\u5929\u84dd,\u6df1\u6e56\u84dd,\u52ff\u5fd8\u8349,\u6df1\u7af9\u6708,\u4eae\u6d77\u84dd,\u677e\u77f3\u7eff,\u6d77\u6d0b\u84dd,\u6e05\u6c34\u84dd,\u4e2d\u6e56\u84dd,\u7389\u77f3\u84dd,\u82cd\u9752,\u5343\u8349,\u6d45\u7f25,\u6d77\u7eff,\u87f9\u9752,\u6d77\u84dd,\u6c34\u9e2d,\u6e56\u84dd,\u5929\u84dd,\u6c34\u6676,\u7ed2\u84dd,\u94c1\u84dd,\u851a\u84dd,\u7c89\u84dd,\u9732\u8349,\u975b,\u6c34">\u5929\u84dd\u8272</value>
            <value altvalues="\u90a3\u74e6\u970d\u767d,\u6d45\u77f3\u677f\u7070,\u7070\u79cb\u9e92\u9e9f,\u5ae9\u59dc\u9ec4,\u7070\u91d1\u83ca,\u67e0\u6aac\u7ef8,\u5bcc\u6625\u7eba,\u8c61\u7259\u9ec4,\u7389\u7c73\u4e1d,\u9676\u576f\u9ec4,\u7a3b\u8349\u9ec4,\u7eff\u9ec4,\u6c99\u6ee9,\u6de1\u7c73,\u80e1\u7c89,\u4e73\u9ec4,\u7c73\u9ec4,\u5208\u5b89,\u8584\u82b1,\u674f,\u6c99">\u7c73\u9ec4\u8272</value>
            <value altvalues="\u56fd\u9645\u514b\u83b1\u56e0\u84dd,\u677f\u5ca9\u6697\u84dd\u7070,\u6df1\u5ca9\u6697\u84dd\u7070,\u666e\u9c81\u58eb\u84dd,\u95f4\u6697\u84dd,\u6697\u77ff\u84dd,\u6df1\u7070\u84dd,\u6c34\u624b\u84dd,\u6d77\u519b\u84dd,\u5348\u591c\u84dd,\u7687\u519b\u84dd,\u6df1\u9752\u83b2,\u6697\u6d77\u5170,\u7ec0\u6854\u6897,\u77ff\u84dd,\u519b\u5170,\u6df1\u5170,\u975b\u9752,\u84dd\u94c1,\u6e5b\u84dd,\u6854\u6897,\u7ec0\u84dd,\u9edb\u84dd,\u85cf\u9752,\u54c1\u84dd,\u6d77\u519b,\u6697\u9752,\u4e2d\u84dd,\u94c1\u7ec0,\u6df1\u84dd,\u6d53\u84dd,\u975b\u84dd,\u6c99\u9752,\u58a8\u84dd,\u85cf\u84dd,\u7409\u7483,\u6697\u84dd,\u9edb,\u7ec0">\u6df1\u84dd\u8272</value>
            <value altvalues="\u97e6\u5947\u4f0d\u5fb7\u74f7\u84dd,\u6697\u5a74\u513f\u7c89\u84dd,\u7231\u4e3d\u4e1d\u84dd,\u8428\u514b\u65af\u84dd,\u5a74\u513f\u7c89\u84dd,\u6de1\u94a2\u84dd,\u6d45\u7d2b\u84dd,\u6697\u7070\u84dd,\u519b\u670d\u84dd,\u77f3\u78e8\u84dd,\u7409\u7483\u7ec0,\u95f4\u6d77\u84dd,\u4eae\u94a2\u84dd,\u4eae\u5929\u84dd,\u4eae\u94a2\u5170,\u5b54\u96c0\u84dd,\u706b\u836f\u84dd,\u4e2d\u78a7\u84dd,\u7c89\u672b\u84dd,\u4eae\u6d77\u7eff,\u4e2d\u5ca9\u84dd,\u519b\u6821\u84dd,\u51b0\u96ea\u84dd,\u6d45\u6e56\u84dd,\u7af9\u6708,\u58a8\u7070,\u6c34\u84dd,\u9752\u84dd,\u78a7\u84dd,\u94a2\u84dd,\u74ee\u8997,\u84dd\u7070,\u6de1\u84dd,\u6d45\u84dd,\u83d8\u84dd,\u77f3\u84dd,\u6625\u84dd,\u6708\u767d,\u7a7a">\u6d45\u84dd\u8272</value>
            <value altvalues="\u706f\u8349\u7070,\u9ed1\u53e4\u94dc,\u6a44\u6984\u9ed1,\u4e4c\u8d3c\u58a8,\u767e\u8349\u971c,\u53e4\u94dc\u9ed1,\u6cb9\u70df\u58a8,\u9edd\u9ed1,\u9ed2\u6a61,\u9752\u9ed1,\u78b3\u9ed1,\u9ed2\u7d2b,\u4e4c\u9ed1,\u94c1\u9ed1,\u7164\u9ed1,\u6697\u9ed1,\u7eaf\u9ed1,\u70df\u6817,\u571f\u9ed1,\u6f06\u9ed1,\u6df1\u9ed1,\u7d2b\u9ed2,\u58a8,\u9eef,\u9ed2,\u9edd,\u9ed1">\u9ed1\u8272</value>
            <value altvalues="\u91d1\u9e92\u9e9f,\u9999\u69df\u9ec4,\u5e93\u91d1,\u9ec4\u91d1,\u9999\u69df,\u91d1">\u91d1\u8272</value>
            <value altvalues="\u8461\u8404\u7070,\u5361\u5176\u5e03,\u6df1\u94f6\u7070,\u5361\u5176\u9ec4,\u4e39\u4e1c\u77f3,\u8299\u84c9\u7ea2,\u9e20\u7fbd\u9f20,\u4eae\u5361\u5176,\u4e2d\u68d5\u7070,\u6d45\u5361\u5176,\u9ec4\u67af\u8336,\u9e7f\u76ae\u978b,\u6d45\u68d5\u8336,\u4e73\u68d5,\u867e\u7070,\u5976\u6cb9,\u7070\u7c73,\u7070\u9ec4,\u7c73\u7070,\u9752\u91d1,\u82bd\u7070,\u874b\u767d,\u9e1f\u5b50,\u674f\u4ec1,\u8089\u68d5,\u9752\u767d,\u9a7c\u7070,\u9752\u9ec4,\u5361\u5176,\u679d\u9ec4,\u8c61\u7259,\u4e73\u7070,\u751f\u6210,\u9ece,\u9a7c">\u6d45\u5361\u5176\u8272</value>
            <value altvalues="\u7c97\u6676\u7680,\u7c97\u6676\u7682,\u627f\u5fb3\u7070,\u7d2b\u85e4\u7070,\u627f\u5fb7\u7070,\u9e4a\u7070,\u9ed2\u94c1,\u9e26\u9752,\u82cd\u9ed1,\u6d53\u9f20,\u8584\u67ff,\u6df1\u7070,\u94c1\u7070,\u87f9\u7070,\u94c5\u7070,\u9752\u7070,\u78b3\u7070,\u9ed1\u8910,\u9ed1\u7070,\u874b,\u7070">\u6df1\u7070\u8272</value>
            <value altvalues="\u9c7c\u809a\u767d,\u82b1\u5349\u767d,\u674f\u4ec1\u767d,\u6d77\u8d1d\u58f3,\u7f8a\u6bdb\u767d,\u7389\u77f3\u767d,\u7acb\u5fb3\u7c89,\u84b2\u516c\u82f1,\u53e4\u8463\u767d,\u8c61\u7259\u767d,\u82cd\u767d,\u837c\u767d,\u82b1\u767d,\u6f02\u767d,\u7cbe\u767d,\u83b9\u767d,\u70df\u767d,\u51c0\u767d,\u7eaf\u767d,\u7d20\u767d,\u96ea\u767d,\u6d01\u767d,\u8721\u767d,\u767d\u70df,\u950c\u767d,\u767d\u674f,\u767d,\u96ea">\u767d\u8272</value>
            <value altvalues="\u6df1\u7eff\u5b9d\u77f3,\u7c97\u5b54\u96c0\u7eff,\u67e5\u7279\u9152\u7eff,\u5e38\u6625\u85e4\u7eff,\u5b54\u96c0\u77f3\u7eff,\u5a01\u5c3c\u65af\u7eff,\u95f4\u7eff\u5b9d\u77f3,\u6df1\u6d77\u6d0b\u7eff,\u94dc\u9508\u7eff,\u8349\u576a\u7eff,\u871c\u74dc\u7eff,\u4e2d\u6625\u7eff,\u6d0b\u84df\u7eff,\u4e2d\u6d77\u7eff,\u7eff\u5b9d\u77f3,\u677e\u82b1\u7eff,\u9752\u74f7\u7eff,\u6a59\u7eff\u4ee5,\u78a7\u7389\u77f3,\u9178\u6a59\u7eff,\u8349\u5730\u7eff,\u9178\u6027\u7eff,\u6d77\u6d0b\u7eff,\u9e66\u9e49\u7eff,\u82d4\u85d3\u7eff,\u7eff\u7409\u7483,\u6df1\u82bd\u7eff,\u539f\u91ce\u7eff,\u5df4\u9ece\u7eff,\u677e\u67cf\u7eff,\u68ee\u6797\u7eff,\u5ae9\u8349\u7eff,\u67e0\u6aac\u7eff,\u6c34\u8349\u7eff,\u82e6\u74dc\u7eff,\u7fe1\u7fe0,\u8349\u7eff,\u94ec\u7eff,\u9752\u8471,\u94dc\u7eff,\u6cb9\u7eff,\u6728\u8d3c,\u5e38\u76d8,\u67f3\u7eff,\u8001\u7eff,\u5ae9\u7eff,\u7eff\u6c88,\u591c\u7eff,\u7389\u7eff,\u7eff\u7389,\u6625\u7eff,\u65b0\u82bd,\u4eae\u7eff,\u6bdb\u7eff,\u9c9c\u7eff,\u9752\u78a7,\u4e2d\u7eff,\u660e\u7eff,\u82e5\u7eff,\u679d\u7eff,\u8584\u7eff,\u95f4\u7eff,\u78a7\u7eff,\u9752\u7fe0,\u82cd\u7eff,\u9549\u7eff,\u8471\u7eff,\u9752\u7eff,\u6df1\u7eff,\u82cd\u7fe0,\u7eff\u6c89,\u94b4\u7eff,\u7eaf\u7eff,\u53f6\u7eff,\u77f3\u7eff,\u7af9\u9752,\u7070\u7eff,\u67f3,\u74dc,\u7eff,\u82d4,\u8349">\u7eff\u8272</value>
            <value altvalues="\u8c61\u7259\u9ed1,\u4ed9\u658e\u8336,\u4eae\u5ca9\u7070,\u627f\u5fb7\u7682,\u5361\u5176\u7070,\u7ec7\u9526\u7070,\u4e2d\u7070\u5170,\u6c34\u8c82\u7070,\u6c34\u6ce5\u7070,\u77f3\u677f\u7070,\u6d45\u83b2\u7070,\u5229\u4f11\u9f20,\u6df1\u74e6\u7070,\u8584\u58a8,\u8c46\u7070,\u94f6\u7b94,\u8584\u9f20,\u660f\u7070,\u6b63\u7070,\u5ca9\u7070,\u8001\u94f6,\u7070\u84dd,\u4e2d\u7070,\u9f20\u7070,\u679c\u7070,\u6697\u7070,\u8584\u949d,\u5929\u7070,\u70df\u7070,\u85d5\u7070,\u94f6\u9f20,\u84dd\u9f20,\u94c1">\u4e2d\u7070\u8272</value>
            <value altvalues="\u6d45\u79cb\u9e92\u9e9f\u9ec4,\u67e0\u6aac\u8584\u7eb1,\u542b\u7f9e\u8349\u9ec4,\u4e1d\u74dc\u82b1\u9ec4,\u5411\u65e5\u8475,\u67e0\u6aac\u9ec4,\u82a5\u672b\u9ec4,\u4eae\u91d1\u9ec4,\u8309\u8389\u9ec4,\u6d45\u6854\u9ec4,\u79cb\u9e92\u9e9f,\u9e2d\u5375\u9752,\u6a31\u8349\u9ec4,\u5c0f\u9e21\u9ec4,\u6a44\u6984\u9ec4,\u91d1\u9ec4,\u9ec4\u94dc,\u5ae9\u9ec4,\u6d45\u9ec4,\u9c9c\u9ec4,\u7eaf\u9ec4,\u9e45\u9ec4,\u9ec4\u6a97,\u8349\u9ec4,\u6a31\u8349,\u4eae\u9ec4,\u9e2d\u9ec4,\u867e\u9ec4,\u7259\u7eff,\u6de1\u9ec4,\u8273\u9ec4,\u7f1f,\u7f03,\u9ec4,\u9db8,\u7259,\u9999">\u6d45\u9ec4\u8272</value>
            <value altvalues="\u4e4c\u7f57\u677e\u7ea2,\u7d2b\u7f57\u5170\u7ea2,\u8910\u73ab\u7470\u7ea2,\u94f6\u661f\u6d77\u68e0,\u77f3\u69b4\u7ea2,\u7ea2\u5b9d\u77f3,\u5b9d\u77f3\u7ea2,\u6708\u5b63\u7ea2,\u8c61\u7259\u7ea2,\u6a31\u6843\u7ea2,\u7261\u4e39\u7ea2,\u80ed\u8102\u7ea2,\u756a\u8304\u7ea2,\u897f\u7ea2\u67ff,\u8fa3\u6912\u7ea2,\u5c71\u8336\u7ea2,\u73ab\u7470\u7ea2,\u8840\u7259\u7ea2,\u9c91\u9c7c\u7ea2,\u6d45\u82cf\u82b3,\u8543\u8304\u7ea2,\u6cd5\u56fd\u7ea2,\u739b\u7459\u7ea2,\u69b4\u82b1\u7ea2,\u7ea2\u6885,\u7eaf\u7ea2,\u5747\u7ea2,\u5927\u7ea2,\u9c9c\u7ea2,\u7ea2\u8d64,\u82cf\u82b3,\u8840\u7ea2,\u82f9\u679c,\u7329\u7ea2,\u771f\u7ea2,\u4eca\u6837,\u8165\u7ea2,\u6d45\u7ea2,\u8089\u7ea2,\u6bb7\u7ea2,\u6a31\u6843,\u5983\u7ea2,\u7ae0\u4e39,\u7eef\u7ea2,\u7261\u4e39,\u9549\u7ea2,\u756a\u8304,\u9161\u7ea2,\u6de1\u7ea2,\u5ae3\u7ea2,\u66d9\u7ea2,\u8d64\u9516,\u706b\u7ea2,\u8fb0\u6c99,\u5f64,\u7eef,\u6731,\u708e,\u7ea2,\u8d6b,\u8d6d,\u8d64,\u831c">\u7ea2\u8272</value>
            <value altvalues="\u7518\u8349\u9ec4,\u6697\u91d1\u83ca,\u8def\u8003\u8336,\u8010\u706b\u7816,\u7389\u7c73\u9ec4,\u82cd\u9e92\u9e9f,\u756a\u6728\u74dc,\u9ec4\u7409\u7483,\u6708\u9ec4,\u840c\u9ec4,\u67af\u9ec4,\u91d1\u8336,\u8431\u8349,\u86cb\u9ec4,\u7389\u7c73,\u59dc\u9ec4,\u6df1\u9ec4,\u4e2d\u9ec4,\u91d1\u68d5,\u7259\u9ec4,\u8d64\u91d1,\u8702\u871c,\u94b4\u9ec4,\u660f\u9ec4,\u8471\u9ec4,\u9549\u9ec4,\u77f3\u9ec4,\u69d0\u9ec4,\u660e\u9ec4,\u6c34\u9ec4,\u7802\u9ec4,\u79cb\u9999,\u9ec4\u571f,\u82cd\u9ec4,\u9974,\u5375,\u67af,\u6cb9">\u4e2d\u9ec4\u8272</value>
            <value altvalues="\u4e07\u5bff\u83ca\u9ec4,\u4eae\u91d1\u83ca\u9ec4,\u5357\u74dc\u9ec4,\u65e5\u5149\u9ec4,\u6df1\u6854\u9ec4,\u70ed\u5e26\u6a59,\u6697\u91d1\u9ec4,\u6697\u6854\u9ec4,\u571f\u9ec4,\u91d1\u8d64,\u7c89\u6a59,\u9ec4\u8d64,\u90c1\u91d1,\u5c71\u5439,\u9633\u6a59,\u571f\u5668,\u6a59\u9ec4,\u8001\u82b1,\u94ec\u9ec4,\u82a6\u9ec4,\u6842\u76ae,\u6697\u9ec4,\u6a58\u9ec4,\u94c1\u9ec4,\u96c4\u9ec4,\u7425\u73c0,\u91d1\u83ca,\u85e4\u9ec4,\u67d1\u5b50,\u6d45\u6a59,\u674f\u9ec4,\u6854\u9ec4,\u72d0,\u6854,\u6a59,\u6a58,\u571f">\u6a58\u9ec4\u8272</value>
            <value altvalues="\u56fd\u9645\u5947\u8fde\u84dd,\u5929\u9752\u77f3\u84dd,\u6781\u6d53\u6d77\u84dd,\u84dd\u5b9d\u77f3,\u6708\u5149\u84dd,\u58eb\u6797\u84dd,\u7687\u5bb6\u84dd,\u5317\u4eac\u84dd,\u5b9d\u77f3\u84dd,\u94b4\u84dd,\u7fa4\u9752,\u4eae\u84dd,\u7eaf\u84dd,\u95ea\u5170,\u5b9d\u84dd,\u9c9c\u84dd,\u5f69\u84dd,\u5170,\u84dd">\u84dd\u8272</value>
            <value altvalues="\u9cdd\u9c7c\u9ec4,\u6d45\u9ec4\u68d5,\u9a6c\u978d\u68d5,\u4e9a\u9ebb\u5e03,\u4e01\u5b50\u8336,\u9ec4\u571f\u8d6d,\u4e9a\u9ebb,\u9ec4\u8910,\u6d45\u8910,\u65e5\u6652,\u6de1\u8910,\u5c0f\u9ea6,\u6c99\u68d5,\u7070\u571f,\u9ec4\u6a61,\u7126\u9999,\u4e4c\u91d1,\u7d2b\u94dc,\u9a86\u9a7c,\u6a59\u8910,\u6d45\u68d5,\u82a5\u5b50,\u7eb8\u68d5,\u7ea2\u72d0,\u6a80\u9999,\u9ec4\u68d5,\u571f\u7070,\u4e2d\u9a7c,\u4e01\u5b50,\u68d5\u8336,\u53e4\u91d1,\u68d5\u9ec4,\u786c\u6728,\u6728">\u6d45\u68d5\u8272</value>
            <value altvalues="\u6697\u5b9d\u77f3\u7eff,\u84dd\u6d77\u677e\u8336,\u94c1\u5fa1\u7eb3\u6237,\u6df1\u77f3\u677f\u7070,\u6697\u6a44\u6984\u7eff,\u7070\u6e56\u7eff,\u6697\u6d77\u7eff,\u9752\u767d\u6a61,\u6697\u82d4\u7eff,\u6de1\u7070\u7eff,\u6df1\u677e\u7eff,\u6df1\u7fe0\u7eff,\u5343\u6b73\u7eff,\u6df1\u7eff\u8910,\u6697\u5ca9\u7070,\u58a8\u7389\u7eff,\u5fa1\u7eb3\u6237,\u7fe0\u7eff,\u9516\u9f20,\u9edb\u7eff,\u58a8\u7eff,\u51eb\u7eff,\u9eb9\u5c18,\u9244\u7eff,\u8584\u7f25,\u82d4\u7070,\u840c\u8471,\u8336\u7eff,\u8910\u8fd4,\u6697\u7eff">\u58a8\u7eff\u8272</value>
            <value altvalues="\u6d45\u77f3\u82f1\u7d2b,\u6de1\u7d2b\u4e01\u9999,\u6d45\u7070\u7d2b\u7ea2,\u6d45\u51e4\u4ed9\u7d2b,\u85b0\u8863\u8349\u7d2b,\u94c1\u7ebf\u83b2\u7d2b,\u4e09\u8272\u5807\u7d2b,\u73ab\u7470\u7d2b\u7ea2,\u73ab\u7470\u7d2b,\u53e4\u4ee3\u7d2b,\u85e4\u7eb3\u6237,\u6697\u5170\u7d2b,\u6728\u69ff\u7d2b,\u9752\u83b2\u7d2b,\u6d45\u85e4\u7d2b,\u4e2d\u5170\u7d2b,\u7d2b\u4e01\u9999,\u6df1\u7d2b\u7ea2,\u7275\u725b\u7d2b,\u96ea\u9752\u7070,\u8304\u76ae\u7d2b,\u8461\u8404\u9f20,\u7d2b\u6c34\u6676,\u7d2b\u7f57\u5170,\u6697\u6d0b\u7ea2,\u7d2b\u8587\u82b1,\u4e01\u9999\u7d2b,\u5170\u82b1\u7d2b,\u4e2d\u7d2b\u7ea2,\u4e01\u9999,\u9752\u7d2b,\u94b4\u7d2b,\u7d2b\u68e0,\u6de1\u7d2b,\u85d5\u8377,\u7d2b\u9171,\u96ea\u9752,\u9c9c\u7d2b,\u6d0b\u674e,\u4eae\u7d2b,\u675c\u82e5,\u5170\u7d2b,\u77ff\u7d2b,\u8461\u8404,\u85e4\u7d2b,\u7ea2\u7d2b,\u4e8c\u84dd,\u6d45\u7d2b,\u84df\u7d2b,\u9752\u83b2,\u9171\u7d2b,\u96ea\u7d2b,\u4e4c\u7d2b,\u9e20\u7fbd,\u674e\u7d2b,\u5ca9\u84dd,\u7d2b\u85e4,\u85e4,\u80dc,\u83eb,\u4e4c,\u7d2b">\u7d2b\u8272</value>
            <value altvalues="\u5176\u5b83,\u5176\u4ed6">\u5176\u4ed6</value>
            <value altvalues="\u6697\u7eff\u677e\u77f3,\u4e2d\u6761\u867e\u7eff,\u7eff\u677e\u77f3\u7eff,\u5c06\u6821\u5462,\u5361\u5176\u7eff,\u5927\u8d64\u91d1,\u6df1\u8349\u7eff,\u6c34\u6676\u7eff,\u51ac\u74dc\u7eff,\u6a44\u6984\u7eff,\u677e\u53f6,\u677e\u7eff,\u56fd\u9632,\u8910\u7eff,\u6d77\u677e,\u83ba\u8336,\u62b9\u8336,\u68d5\u7eff,\u9db8\u8336,\u5c71\u9e20,\u519b\u7eff,\u51ac\u7eff,\u9752\u4e39,\u4f3d\u7f57,\u6a44\u6984,\u83ba">\u519b\u7eff\u8272</value>
            <value altvalues="\u9e21\u51a0\u82b1\u7ea2,\u5370\u7b2c\u5b89\u7ea2,\u7ea2\u6d77\u8001\u8336,\u8010\u706b\u7816\u7ea2,\u5a01\u5c3c\u65af\u7ea2,\u91c9\u5e95\u7ea2,\u90ce\u7a91\u7ea2,\u8c49\u8c46\u7ea2,\u6df1\u70df\u7ea2,\u6d77\u87ba\u7ea2,\u73b3\u7441\u7ea2,\u9ad8\u7cb1\u7ea2,\u58a8\u7edb\u7ea2,\u94c1\u9508\u7ea2,\u6697\u7edb\u7ea2,\u6df1\u91c9\u7ea2,\u6d0b\u7ea2,\u9152\u7ea2,\u6697\u7ea2,\u6df1\u7ea2,\u9508\u7ea2,\u8d6d\u77f3,\u67a3\u7ea2,\u8d6b\u8d64,\u571f\u7ea2,\u5f01\u67c4,\u80e1\u6843,\u7d2b\u6a80,\u7816\u7ea2,\u80ed\u8102,\u54c1\u7ea2,\u5c0f\u8c46,\u4e8c\u6731,\u706b\u7816,\u6731\u7802,\u706d\u7d2b,\u94c1\u7ea2,\u8549\u7ea2,\u685c">\u6df1\u7ea2\u8272</value>
            <value altvalues="\u94f6\u7070,\u94f6\u767d,\u8336\u9f20,\u950c,\u94f6">\u94f6\u8272</value>
            <value altvalues="\u5e9a\u65af\u535a\u7f57\u7070,\u6d45\u7c73\u7070,\u5e7d\u7075\u767d,\u6d45\u68d5\u7070,\u9e3d\u5b50\u7070,\u73cd\u73e0\u767d,\u7261\u86ce\u767d,\u950c\u94a1\u767d,\u7eb3\u74e6\u767d,\u4eae\u84dd\u7070,\u9e7f\u76ae,\u7070\u767d,\u672c\u767d,\u96fe\u7070,\u94c5\u767d,\u82b1\u7070,\u7c73\u7ef8,\u767d\u7070,\u4eae\u7070,\u673d\u53f6,\u96ea\u7070,\u4e73\u767d,\u7070\u77f3,\u6930\u8910,\u6de1\u7070,\u7c89\u68d5,\u6d45\u7070,\u7c73\u767d,\u7c73,\u79d8,\u8584,\u7d20,\u971c,\u77f3,\u9f20,\u7802,\u7efe,\u9ebb,\u6bdb">\u6d45\u7070\u8272</value>
            <value altvalues="\u6cd5\u56fd\u68a7\u6850\u76ae,\u6a44\u6984\u519b\u670d\u7eff,\u6df1\u5361\u5176\u5e03,\u6a44\u6984\u571f\u8910,\u5ead\u9662\u74e6\u7070,\u7a7a\u4e94\u500d\u5b50,\u7f57\u6c49\u679c,\u6a44\u6984\u7070,\u6df1\u5361\u5176,\u76f8\u601d\u7070,\u6697\u5361\u5176,\u6d45\u7070\u8910,\u73c8\u7432\u68d5,\u571f\u8910,\u5a9a\u8336,\u7070\u8910,\u751f\u58c1,\u9752\u8910,\u6728\u5170,\u756a\u6728,\u4e9c\u9ebb,\u9ec4\u680c,\u6c99\u8910,\u67af\u8336,\u94c5,\u79cb,\u9769,\u9516,\u9ee7,\u6d85">\u6df1\u5361\u5176\u8272</value>
            <value altvalues="\u9f99\u6cc9\u9752\u74f7\u91c9,\u6d45\u6d77\u6d0b\u7eff,\u8584\u8377\u5976\u6cb9,\u4eae\u67e0\u6aac\u7eff,\u82cd\u5b9d\u77f3\u7eff,\u6d45\u6c34\u7eff,\u6d45\u8349\u7eff,\u6d45\u7eff\u7070,\u6d45\u9c9c\u7eff,\u6c34\u6d45\u8471,\u6d45\u8c46\u6c99,\u5ae9\u8471\u7eff,\u82f9\u679c\u7eff,\u9516\u6d45\u8471,\u6d45\u677e\u7eff,\u5929\u6c34\u78a7,\u6d77\u6c34\u7eff,\u87f9\u58f3\u9752,\u8377\u830e\u7eff,\u6d45\u8c46\u7eff,\u9752\u53e4\u94dc,\u9752\u7eff,\u9752\u7af9,\u67f3\u9ec4,\u677e\u82b1,\u54c1\u7eff,\u9ec4\u7070,\u679c\u7eff,\u6c99\u7eff,\u82a6\u7070,\u767d\u7eff,\u8471\u5029,\u5143\u9752,\u4e09\u7eff,\u9752\u8c46,\u5229\u4e45,\u827e\u7eff,\u5976\u7eff,\u6c34\u7eff,\u7eff\u9ec4,\u9508\u7eff,\u6d45\u7eff,\u77f3\u9752,\u9178\u6a59,\u82e5\u7af9,\u9ec4\u7eff,\u67af\u7eff,\u82e5\u8349,\u6de1\u7eff,\u82a5\u672b,\u6768\u6843,\u9752\u867e,\u8c46\u7eff,\u7f25,\u82cd,\u82d7,\u7389">\u6d45\u7eff\u8272</value>
            <value altvalues="\u6d45\u9752\u74f7\u91c9,\u8584\u8377\u7eff,\u9e2d\u86cb\u9752,\u7eff\u677e\u77f3,\u95f4\u6625\u7eff,\u4eae\u9752,\u9edb\u9752,\u65b0\u6865,\u5927\u9752,\u82b1\u9752,\u8471\u9752,\u7eff\u9752,\u86cb\u9752,\u94c1\u9752,\u9c9c\u9752,\u5929\u9752,\u6d45\u9752,\u9701\u9752,\u5f71\u9752,\u94a2\u5170,\u6df1\u9752,\u7c89\u9752,\u6de1\u9752,\u7eff\u84dd,\u6e56\u7eff,\u7ec0\u9752,\u8584\u8377,\u94a2\u9752,\u8c46\u9752,\u9752\u78c1,\u6d45\u8471,\u84dd\u7eff,\u767d\u7fa4,\u83ca\u5170,\u78a7,\u9752">\u9752\u8272</value>
            <value altvalues="\u73ab\u7470\u8910,\u9e7f\u76ae\u68d5,\u5de7\u53ef\u529b,\u9cdd\u9c7c\u9752,\u6d77\u8001\u8336,\u5de7\u514b\u529b,\u68d5\u8910,\u53e4\u94dc,\u79d8\u9c81,\u8336\u8910,\u6817\u8910,\u6652\u9ed1,\u978d\u8910,\u7164\u7af9,\u68d5\u7ea2,\u5496\u5561,\u6867\u76ae,\u8336\u9752,\u7070\u8336,\u5b9e\u6728,\u9ec4\u8336,\u6817,\u8910,\u7c9f,\u68d5">\u8910\u8272</value>
            <value altvalues="\u82cd\u7d2b\u7f57\u5170,\u6df1\u5170\u82b1\u7d2b,\u6df1\u7d2b\u7f57\u5170,\u67cf\u574a\u7070\u84dd,\u6697\u7d2b\u7f57\u5170,\u6df1\u7d2b\u7070,\u6697\u5ca9\u84dd,\u8461\u8404\u7d2b,\u9f99\u80c6\u7d2b,\u7d2b\u7f57\u84dd,\u6df1\u7d2b,\u9edb\u87ba,\u7384\u9752,\u9edb\u7d2b,\u8d64\u7d2b,\u84dd\u7d2b,\u9752\u949d,\u7d2b\u84dd,\u6697\u7d2b,\u58a8\u7d2b,\u7d2b\u7ec0,\u7ec0\u7d2b,\u7d2b\u7070">\u6df1\u7d2b\u8272</value>
            <value altvalues="\u5370\u5ea6\u7ea2,\u4eae\u9c91\u7ea2,\u6697\u9c91\u7ea2,\u67ff\u5b50\u6a59,\u7ea2\u6247\u8d1d,\u70ed\u7c89\u7ea2,\u6d45\u7edb\u7ea2,\u73ca\u745a\u7ea2,\u6de1\u73ca\u745a,\u831c\u7ea2,\u6a59\u7ea2,\u6a58\u7ea2,\u6df1\u6a59,\u94c1\u9508,\u6768\u5983,\u9c91\u7ea2,\u8d64\u8910,\u9ec4\u4e39,\u7ea2\u7682,\u9161\u989c,\u6697\u6a59,\u739b\u7459,\u71c3\u6a59,\u871c\u6a59,\u94f6\u6731,\u91d1\u7ea2,\u7ea2\u6866,\u771f\u8d6d,\u6800\u5b50,\u6854\u7ea2,\u8fb0\u7802,\u674f\u7ea2,\u6cb9\u7ea2,\u871c\u67d1,\u82cf\u6728,\u6854\u68d5,\u96c4\u7cbe,\u73ca\u745a,\u8d64\u6a59,\u6731\u7ea2,\u67ff\u5b50,\u94c5\u4e39,\u91c9\u7ea2,\u4ee3\u8d6d,\u94ec\u7ea2,\u6d17\u6731,\u6731\u8198,\u7ea2\u6a59,\u70bc\u74e6,\u66d9,\u67ff,\u6a80,\u6866,\u4e39,\u5983">\u6a59\u7ea2\u8272</value>
            <value altvalues="\u6d0b\u73ab\u7470\u7ea2,\u4e2d\u9752\u7d2b\u7ea2,\u6d45\u73ab\u7470\u7ea2,\u8309\u8389\u82b1\u7ea2,\u4f18\u54c1\u7d2b\u7ea2,\u6d77\u68e0\u7ea2,\u6df1\u6d0b\u7ea2,\u7ea2\u7070\u83b2,\u6df1\u85d5\u7ea2,\u7f2c\u8349\u7d2b,\u7ea2\u83b2\u7070,\u6d45\u83b2\u7ea2,\u73ab\u7470\u7070,\u6d0b\u8471\u7d2b,\u6696\u7c89\u7ea2,\u67a2\u673a\u7ea2,\u9526\u8475\u7d2b,\u6de1\u7d2b\u7ea2,\u7d2b\u6247\u8d1d,\u4eae\u7c89\u7ea2,\u6843\u7ea2,\u7d2b\u7edb,\u6885\u7ea2,\u7d2b\u7c89,\u7edb\u7d2b,\u73ab\u7ea2,\u6c34\u7ea2,\u7d2b\u7ea2,\u8e2f\u8e85,\u674e\u5b50,\u94f6\u7ea2,\u77f3\u7af9,\u8273\u7c89,\u67a3\u7d2b,\u8d6d\u7ea2,\u8d64\u4e39,\u6df1\u7c89,\u7ea2\u7eef,\u8336">\u73ab\u7ea2\u8272</value>
            <value altvalues="\u85b0\u8863\u8349\u7d2b\u7ea2,\u5c16\u6676\u77f3\u7ea2,\u6d45\u73cd\u73e0\u7ea2,\u8584\u96fe\u73ab\u7470,\u6d45\u73ca\u745a\u7ea2,\u5341\u6837\u9526,\u706b\u9e64\u7ea2,\u6de1\u85d5\u5408,\u51e4\u4ed9\u7c89,\u8584\u7ea2\u6885,\u6d45\u9c91\u7ea2,\u6d45\u9c9c\u8089,\u6de1\u7d2b\u767d,\u6de1\u7d2b\u7070,\u6d45\u73ab\u7470,\u7518\u77f3\u7c89,\u8089\u68d5\u7070,\u6de1\u767d\u7d2b,\u8377\u82b1\u7ea2,\u6df1\u9c9c\u8089,\u6df1\u7c89\u7ea2,\u957f\u6625\u82b1,\u8d64\u767d\u6a61,\u6d45\u7c89\u7ea2,\u6d45\u8089\u7c89,\u86e4\u870a\u7c89,\u7c89\u7ea2\u767d,\u96fe\u73ab\u7470,\u7c89\u51e4\u4ed9,\u7070\u7d2b\u7ea2,\u6c5f\u6237\u7d2b,\u4eae\u73ca\u745a,\u6d45\u8840\u7259,\u58f3\u9ec4\u7ea2,\u65e7\u857e\u4e1d,\u739b\u7459\u7c89,\u7c89\u6251\u6843,\u9000\u7ea2,\u7c73\u7ea2,\u7c89\u7ea2,\u767d\u7c89,\u6de1\u7c89,\u4eae\u8089,\u8089\u7c89,\u6d45\u9a7c,\u6d17\u67ff,\u6697\u7c89,\u5976\u68d5,\u83b2\u7ea2,\u83d6\u84b2,\u8537\u8587,\u6d77\u8d1d,\u8c46\u6c99,\u9c9c\u8089,\u86e4\u7c89,\u7c89\u767d,\u6e58\u5983,\u8089\u9ec4,\u8089\u6842,\u6d45\u7c89,\u88f8\u80a4,\u6697\u8089,\u83b2\u7070,\u6843,\u7c89,\u808c,\u85d5,\u871c,\u84df,\u9e28,\u4eba,\u8089">\u7c89\u7ea2\u8272</value>
            <value altvalues="\u52c3\u826e\u7b2c\u9152\u7ea2,\u6731\u53e4\u529b,\u6a44\u6984\u68d5,\u73ab\u7470\u68d5,\u6697\u6df1\u7ea2,\u94f6\u7164\u7af9,\u94c1\u9508\u68d5,\u6697\u9ec4\u8910,\u8304\u5b50\u7ec0,\u6866\u8336,\u8d64\u94dc,\u7ea2\u68d5,\u6df1\u7eef,\u6df1\u70df,\u9ed2\u8336,\u91cd\u8910,\u8d64\u8336,\u6df1\u8910,\u8c46\u68d5,\u6817\u6885,\u7d2b\u8910,\u8349\u7070,\u6df1\u6817,\u7126\u8336,\u68d5\u9ed1,\u6697\u8910,\u7f01,\u9e22,\u9171,\u91a4,\u7384">\u6df1\u8910\u8272</value>
        </values>
    </field>
    <field>
        <key>print</key>
        <actions>
            <action>remove-escapechar</action>
            <action>case-insensitive</action>
        </actions>
        <values>
            <value altvalues ="\u5176\u5b83,\u5176\u4ed6,\u4e0d\u89c4\u5219">\u5176\u4ed6</value>
            <value altvalues ="\u62fc\u8272/\u649e\u8272,\u62fc\u63a5,\u62fc\u8272">\u62fc\u8272</value>
            <value altvalues ="\u690d\u7269\u82b1\u5349,\u82b1\u5349,\u5c0f\u6ee1\u82b1">\u690d\u7269</value>
            <value altvalues ="\u5361\u901a\u52a8\u6f2b,\u5361\u901a">\u5361\u901a</value>
            <value altvalues ="\u6c11\u65cf\u98ce\u82b1\u578b,3D\u6548\u679c,\u788e\u82b1">\u5370\u82b1</value>
            <value altvalues ="\u52a8\u7269\u56fe\u6848,\u52a8\u7269\u7eb9,\u52a8\u7269,\u5343\u9e1f\u683c">\u52a8\u7269</value>
            <value altvalues ="\u7eaf\u8272">\u7eaf\u8272</value>
            <value altvalues ="\u6761\u7eb9,\u7ec6\u6a2a\u6761\u7eb9,\u7c97\u6a2a\u6761\u7eb9,\u7ad6\u6761\u7eb9">\u6761\u7eb9</value>
            <value altvalues ="\u683c\u5b50">\u683c\u5b50</value>
            <value altvalues ="\u4eba\u7269,\u9ab7\u9ac5,\u8138\u8c31">\u4eba\u7269</value>
            <value altvalues ="\u54c1\u724cLOGO">\u54c1\u724cLOGO</value>
            <value altvalues ="\u5b57\u6bcd,\u5b57\u6bcd\u6570\u5b57">\u5b57\u6bcd</value>
            <value altvalues ="\u51e0\u4f55,\u51e0\u4f55\u56fe\u6848,\u6761\u7eb9">\u51e0\u4f55</value>
            <value altvalues ="\u82b1\u5349,\u82b1\u8272,\u82b1\u6735,3D\u5370\u82b1,\u5927\u82b1">\u82b1\u5349</value>
            <value altvalues ="\u6ce2\u70b9,\u5706\u70b9">\u5706\u70b9</value>
            <value altvalues ="\u6c34\u58a8\u753b">\u98ce\u666f</value>
            <value altvalues ="\u8c79\u7eb9">\u8c79\u7eb9</value>
            <value altvalues ="\u6cb9\u753b">\u6cb9\u753b</value>
            <value altvalues ="\u6591\u9a6c\u7eb9">\u6591\u9a6c\u7eb9</value>
            <value altvalues ="\u62bd\u8c61\u56fe\u6848">\u56fe\u6848</value>
            <value altvalues ="\u624b\u7ed8,\u6d82\u9e26,\u7d20\u63cf\u624b\u7ed8">\u6d82\u9e26</value>
            <value altvalues ="\u5f62\u72b6">\u5f62\u72b6</value>
            <value altvalues ="\u5fc3\u5f62">\u5fc3\u5f62</value>
            <value altvalues ="\u98ce\u666f">\u98ce\u666f</value>
            <value altvalues ="\u6570\u5b57">\u6570\u5b57</value>
            <value altvalues ="\u8f66\u7f1d\u7ebf">\u8f66\u7f1d\u7ebf</value>
            <value altvalues ="\u683c\u7eb9">\u683c\u7eb9</value>
            <value altvalues ="\u5efa\u7b51">\u5efa\u7b51</value>
            <value altvalues ="\u6e10\u53d8">\u6e10\u53d8</value>
        </values>
    </field>
    <field>
        <key>reviewsize</key>
        <actions>
            <action>case-insensitive</action>
        </actions>
        <values>
            <value altvalues="165/S,160">S</value>
            <value altvalues="170/M,170">M</value>
            <value altvalues="175/L,175">L</value>
            <value altvalues="180/XL,180">XL</value>
            <value altvalues="185/XXL,185">XXL</value>
            <value altvalues="190/3XL,190">3XL</value>
            <value altvalues="195/4XL,195">4XL</value>
        </values>
    </field>
</etl>